[
  {
    "toolName": "Localxpose",
    "measurementNumber": 1,
    "timestamp": 1953163.682143,
    "fileTransfers": [
      {
        "filename": "A_1MB.bin",
        "timestamp": 1953163.687311,
        "fileSize": 1048576,
        "contentType": "application/octet-stream",
        "transferSuccess": true,
        "statusCode": 200,
        "downloadSpeed": 42717,
        "uploadSpeed": 0,
        "dnsLookup": 2.988,
        "tcpConnection": 261.34200000000004,
        "tlsHandshake": 0,
        "timeToFirstByte": 1429.1560000000002,
        "totalTransferTime": 2105.3269999999998,
        "hashMatch": false,
        "sizeMatch": false
      },
      {
        "filename": "random_25MB.bin",
        "timestamp": 1955283.845702,
        "fileSize": 26214400,
        "contentType": "application/octet-stream",
        "transferSuccess": true,
        "statusCode": 200,
        "downloadSpeed": 46209,
        "uploadSpeed": 0,
        "dnsLookup": 15.373,
        "tcpConnection": 217.174,
        "tlsHandshake": 0,
        "timeToFirstByte": 1522.132,
        "totalTransferTime": 1946.226,
        "hashMatch": false,
        "sizeMatch": false
      }
    ],
    "webTests": [
      {
        "url": "http://eb5gynrvuw.loclx.io/webtest",
        "statusCode": 200,
        "downloadSpeed": 49751,
        "uploadSpeed": 0,
        "dnsLookup": 6.603000000000001,
        "tcpConnection": 264.228,
        "tlsHandshake": 0,
        "timeToFirstByte": 1417.989,
        "totalTime": 1807.691,
        "fcp": 1934.5999999940395,
        "lcp": 1934.5999999940395
      }
    ],
    "totalDuration": 152057.03605,
    "setupDuration": 6603.444192999974,
    "diagnosticsDuration": 69.70641799992882,
    "measurementDuration": 135380.75152700022,
    "hasErrors": false,
    "errorCount": 0,
    "errors": []
  },
  {
    "toolName": "Localxpose",
    "measurementNumber": 2,
    "timestamp": 1962181.088283,
    "fileTransfers": [
      {
        "filename": "A_1MB.bin",
        "timestamp": 1962181.095826,
        "fileSize": 1048576,
        "contentType": "application/octet-stream",
        "transferSuccess": true,
        "statusCode": 200,
        "downloadSpeed": 40618,
        "uploadSpeed": 0,
        "dnsLookup": 2.942,
        "tcpConnection": 257.35999999999996,
        "tlsHandshake": 0,
        "timeToFirstByte": 1399.589,
        "totalTransferTime": 2214.163,
        "hashMatch": false,
        "sizeMatch": false
      },
      {
        "filename": "random_25MB.bin",
        "timestamp": 1964408.105512,
        "fileSize": 26214400,
        "contentType": "application/octet-stream",
        "transferSuccess": true,
        "statusCode": 200,
        "downloadSpeed": 51317,
        "uploadSpeed": 0,
        "dnsLookup": 3.4090000000000003,
        "tcpConnection": 200.483,
        "tlsHandshake": 0,
        "timeToFirstByte": 1352.208,
        "totalTransferTime": 1752.52,
        "hashMatch": false,
        "sizeMatch": false
      }
    ],
    "webTests": [
      {
        "url": "http://eb5gynrvuw.loclx.io/webtest",
        "statusCode": 200,
        "downloadSpeed": 38987,
        "uploadSpeed": 0,
        "dnsLookup": 9.934999999999999,
        "tcpConnection": 222.571,
        "tlsHandshake": 0,
        "timeToFirstByte": 1486.5040000000001,
        "totalTime": 2306.761,
        "fcp": 1913.199999988079,
        "lcp": 1913.199999988079
      }
    ],
    "totalDuration": 152057.03605,
    "setupDuration": 6603.444192999974,
    "diagnosticsDuration": 69.70641799992882,
    "measurementDuration": 135380.75152700022,
    "hasErrors": false,
    "errorCount": 0,
    "errors": []
  },
  {
    "toolName": "Localxpose",
    "measurementNumber": 3,
    "timestamp": 1971329.870485,
    "fileTransfers": [
      {
        "filename": "A_1MB.bin",
        "timestamp": 1971329.873768,
        "fileSize": 1048576,
        "contentType": "application/octet-stream",
        "transferSuccess": true,
        "statusCode": 200,
        "downloadSpeed": 37846,
        "uploadSpeed": 0,
        "dnsLookup": 6.946,
        "tcpConnection": 223.86800000000002,
        "tlsHandshake": 0,
        "timeToFirstByte": 1554.802,
        "totalTransferTime": 2376.314,
        "hashMatch": false,
        "sizeMatch": false
      },
      {
        "filename": "random_25MB.bin",
        "timestamp": 1973718.513291,
        "fileSize": 26214400,
        "contentType": "application/octet-stream",
        "transferSuccess": true,
        "statusCode": 200,
        "downloadSpeed": 46519,
        "uploadSpeed": 0,
        "dnsLookup": 9.918,
        "tcpConnection": 219.42999999999998,
        "tlsHandshake": 0,
        "timeToFirstByte": 1519.687,
        "totalTransferTime": 1933.276,
        "hashMatch": false,
        "sizeMatch": false
      }
    ],
    "webTests": [
      {
        "url": "http://eb5gynrvuw.loclx.io/webtest",
        "statusCode": 200,
        "downloadSpeed": 46534,
        "uploadSpeed": 0,
        "dnsLookup": 3.111,
        "tcpConnection": 289.885,
        "tlsHandshake": 0,
        "timeToFirstByte": 1518.921,
        "totalTime": 1932.6380000000001,
        "fcp": 1831.5,
        "lcp": 1831.5
      }
    ],
    "totalDuration": 152057.03605,
    "setupDuration": 6603.444192999974,
    "diagnosticsDuration": 69.70641799992882,
    "measurementDuration": 135380.75152700022,
    "hasErrors": false,
    "errorCount": 0,
    "errors": []
  },
  {
    "toolName": "Localxpose",
    "measurementNumber": 4,
    "timestamp": 1980506.070488,
    "fileTransfers": [
      {
        "filename": "A_1MB.bin",
        "timestamp": 1980506.073841,
        "fileSize": 1048576,
        "contentType": "application/octet-stream",
        "transferSuccess": true,
        "statusCode": 200,
        "downloadSpeed": 42708,
        "uploadSpeed": 0,
        "dnsLookup": 2.719,
        "tcpConnection": 198.16400000000002,
        "tlsHandshake": 0,
        "timeToFirstByte": 1421.192,
        "totalTransferTime": 2105.81,
        "hashMatch": false,
        "sizeMatch": false
      },
      {
        "filename": "random_25MB.bin",
        "timestamp": 1982625.417184,
        "fileSize": 26214400,
        "contentType": "application/octet-stream",
        "transferSuccess": true,
        "statusCode": 200,
        "downloadSpeed": 53107,
        "uploadSpeed": 0,
        "dnsLookup": 5.829,
        "tcpConnection": 196.576,
        "tlsHandshake": 0,
        "timeToFirstByte": 1304.722,
        "totalTransferTime": 1693.452,
        "hashMatch": false,
        "sizeMatch": false
      }
    ],
    "webTests": [
      {
        "url": "http://eb5gynrvuw.loclx.io/webtest",
        "statusCode": 200,
        "downloadSpeed": 40173,
        "uploadSpeed": 0,
        "dnsLookup": 2.8939999999999997,
        "tcpConnection": 222.40099999999998,
        "tlsHandshake": 0,
        "timeToFirstByte": 1457.5059999999999,
        "totalTime": 2238.684,
        "fcp": 1870.2999999821186,
        "lcp": 1870.2999999821186
      }
    ],
    "totalDuration": 152057.03605,
    "setupDuration": 6603.444192999974,
    "diagnosticsDuration": 69.70641799992882,
    "measurementDuration": 135380.75152700022,
    "hasErrors": false,
    "errorCount": 0,
    "errors": []
  },
  {
    "toolName": "Localxpose",
    "measurementNumber": 5,
    "timestamp": 1989523.961886,
    "fileTransfers": [
      {
        "filename": "A_1MB.bin",
        "timestamp": 1989523.965238,
        "fileSize": 1048576,
        "contentType": "application/octet-stream",
        "transferSuccess": true,
        "statusCode": 200,
        "downloadSpeed": 39030,
        "uploadSpeed": 0,
        "dnsLookup": 9.299999999999999,
        "tcpConnection": 211.823,
        "tlsHandshake": 0,
        "timeToFirstByte": 1380.885,
        "totalTransferTime": 2304.205,
        "hashMatch": false,
        "sizeMatch": false
      },
      {
        "filename": "random_25MB.bin",
        "timestamp": 1991844.330299,
        "fileSize": 26214400,
        "contentType": "application/octet-stream",
        "transferSuccess": true,
        "statusCode": 200,
        "downloadSpeed": 42162,
        "uploadSpeed": 0,
        "dnsLookup": 8.449,
        "tcpConnection": 290.03000000000003,
        "tlsHandshake": 0,
        "timeToFirstByte": 1522.424,
        "totalTransferTime": 2133.0789999999997,
        "hashMatch": false,
        "sizeMatch": false
      }
    ],
    "webTests": [
      {
        "url": "http://eb5gynrvuw.loclx.io/webtest",
        "statusCode": 200,
        "downloadSpeed": 46417,
        "uploadSpeed": 0,
        "dnsLookup": 2.699,
        "tcpConnection": 215.798,
        "tlsHandshake": 0,
        "timeToFirstByte": 1343.734,
        "totalTime": 1937.52,
        "fcp": 1830.5,
        "lcp": 1830.5
      }
    ],
    "totalDuration": 152057.03605,
    "setupDuration": 6603.444192999974,
    "diagnosticsDuration": 69.70641799992882,
    "measurementDuration": 135380.75152700022,
    "hasErrors": false,
    "errorCount": 0,
    "errors": []
  },
  {
    "toolName": "Localxpose",
    "measurementNumber": 6,
    "timestamp": 1998669.793992,
    "fileTransfers": [
      {
        "filename": "A_1MB.bin",
        "timestamp": 1998669.801185,
        "fileSize": 1048576,
        "contentType": "application/octet-stream",
        "transferSuccess": true,
        "statusCode": 200,
        "downloadSpeed": 48228,
        "uploadSpeed": 0,
        "dnsLookup": 2.751,
        "tcpConnection": 193.242,
        "tlsHandshake": 0,
        "timeToFirstByte": 1450.834,
        "totalTransferTime": 1864.76,
        "hashMatch": false,
        "sizeMatch": false
      },
      {
        "filename": "random_25MB.bin",
        "timestamp": 2000548.258036,
        "fileSize": 26214400,
        "contentType": "application/octet-stream",
        "transferSuccess": true,
        "statusCode": 200,
        "downloadSpeed": 49113,
        "uploadSpeed": 0,
        "dnsLookup": 4.0920000000000005,
        "tcpConnection": 195.208,
        "tlsHandshake": 0,
        "timeToFirstByte": 1383.329,
        "totalTransferTime": 1831.175,
        "hashMatch": false,
        "sizeMatch": false
      }
    ],
    "webTests": [
      {
        "url": "http://eb5gynrvuw.loclx.io/webtest",
        "statusCode": 200,
        "downloadSpeed": 40225,
        "uploadSpeed": 0,
        "dnsLookup": 2.8800000000000003,
        "tcpConnection": 205.19799999999998,
        "tlsHandshake": 0,
        "timeToFirstByte": 1471.004,
        "totalTime": 2235.782,
        "fcp": 2042.2000000178814,
        "lcp": 2042.2000000178814
      }
    ],
    "totalDuration": 152057.03605,
    "setupDuration": 6603.444192999974,
    "diagnosticsDuration": 69.70641799992882,
    "measurementDuration": 135380.75152700022,
    "hasErrors": false,
    "errorCount": 0,
    "errors": []
  },
  {
    "toolName": "Localxpose",
    "measurementNumber": 7,
    "timestamp": 2007853.478676,
    "fileTransfers": [
      {
        "filename": "A_1MB.bin",
        "timestamp": 2007853.486288,
        "fileSize": 1048576,
        "contentType": "application/octet-stream",
        "transferSuccess": true,
        "statusCode": 200,
        "downloadSpeed": 44956,
        "uploadSpeed": 0,
        "dnsLookup": 6.015000000000001,
        "tcpConnection": 208.238,
        "tlsHandshake": 0,
        "timeToFirstByte": 1484.321,
        "totalTransferTime": 2000.5030000000002,
        "hashMatch": false,
        "sizeMatch": false
      },
      {
        "filename": "random_25MB.bin",
        "timestamp": 2009867.30588,
        "fileSize": 26214400,
        "contentType": "application/octet-stream",
        "transferSuccess": true,
        "statusCode": 200,
        "downloadSpeed": 42159,
        "uploadSpeed": 0,
        "dnsLookup": 5.55,
        "tcpConnection": 289.586,
        "tlsHandshake": 0,
        "timeToFirstByte": 1518.351,
        "totalTransferTime": 2133.216,
        "hashMatch": false,
        "sizeMatch": false
      }
    ],
    "webTests": [
      {
        "url": "http://eb5gynrvuw.loclx.io/webtest",
        "statusCode": 200,
        "downloadSpeed": 44482,
        "uploadSpeed": 0,
        "dnsLookup": 2.928,
        "tcpConnection": 191.40699999999998,
        "tlsHandshake": 0,
        "timeToFirstByte": 1420.6380000000001,
        "totalTime": 2021.7990000000002,
        "fcp": 1913.2999999821186,
        "lcp": 1913.2999999821186
      }
    ],
    "totalDuration": 152057.03605,
    "setupDuration": 6603.444192999974,
    "diagnosticsDuration": 69.70641799992882,
    "measurementDuration": 135380.75152700022,
    "hasErrors": false,
    "errorCount": 0,
    "errors": []
  },
  {
    "toolName": "Localxpose",
    "measurementNumber": 8,
    "timestamp": 2017068.500863,
    "fileTransfers": [
      {
        "filename": "A_1MB.bin",
        "timestamp": 2017068.503727,
        "fileSize": 1048576,
        "contentType": "application/octet-stream",
        "transferSuccess": true,
        "statusCode": 200,
        "downloadSpeed": 46761,
        "uploadSpeed": 0,
        "dnsLookup": 2.444,
        "tcpConnection": 203.90900000000002,
        "tlsHandshake": 0,
        "timeToFirstByte": 1430.2939999999999,
        "totalTransferTime": 1923.273,
        "hashMatch": false,
        "sizeMatch": false
      },
      {
        "filename": "random_25MB.bin",
        "timestamp": 2019006.007121,
        "fileSize": 26214400,
        "contentType": "application/octet-stream",
        "transferSuccess": true,
        "statusCode": 200,
        "downloadSpeed": 49828,
        "uploadSpeed": 0,
        "dnsLookup": 3.573,
        "tcpConnection": 205.424,
        "tlsHandshake": 0,
        "timeToFirstByte": 1391.718,
        "totalTransferTime": 1804.895,
        "hashMatch": false,
        "sizeMatch": false
      }
    ],
    "webTests": [
      {
        "url": "http://eb5gynrvuw.loclx.io/webtest",
        "statusCode": 200,
        "downloadSpeed": 44886,
        "uploadSpeed": 0,
        "dnsLookup": 13.305000000000001,
        "tcpConnection": 207.035,
        "tlsHandshake": 0,
        "timeToFirstByte": 1416.843,
        "totalTime": 2003.587,
        "fcp": 1760,
        "lcp": 1760
      }
    ],
    "totalDuration": 152057.03605,
    "setupDuration": 6603.444192999974,
    "diagnosticsDuration": 69.70641799992882,
    "measurementDuration": 135380.75152700022,
    "hasErrors": false,
    "errorCount": 0,
    "errors": []
  },
  {
    "toolName": "Localxpose",
    "measurementNumber": 9,
    "timestamp": 2025657.586484,
    "fileTransfers": [
      {
        "filename": "A_1MB.bin",
        "timestamp": 2025657.590326,
        "fileSize": 1048576,
        "contentType": "application/octet-stream",
        "transferSuccess": true,
        "statusCode": 200,
        "downloadSpeed": 47070,
        "uploadSpeed": 0,
        "dnsLookup": 2.73,
        "tcpConnection": 194.47,
        "tlsHandshake": 0,
        "timeToFirstByte": 1433.644,
        "totalTransferTime": 1910.659,
        "hashMatch": false,
        "sizeMatch": false
      },
      {
        "filename": "random_25MB.bin",
        "timestamp": 2027582.338187,
        "fileSize": 26214400,
        "contentType": "application/octet-stream",
        "transferSuccess": true,
        "statusCode": 200,
        "downloadSpeed": 45169,
        "uploadSpeed": 0,
        "dnsLookup": 6.787999999999999,
        "tcpConnection": 208.332,
        "tlsHandshake": 0,
        "timeToFirstByte": 1381.282,
        "totalTransferTime": 1991.073,
        "hashMatch": false,
        "sizeMatch": false
      }
    ],
    "webTests": [
      {
        "url": "http://eb5gynrvuw.loclx.io/webtest",
        "statusCode": 200,
        "downloadSpeed": 41317,
        "uploadSpeed": 0,
        "dnsLookup": 7.473999999999999,
        "tcpConnection": 208.68900000000002,
        "tlsHandshake": 0,
        "timeToFirstByte": 1562.174,
        "totalTime": 2176.681,
        "fcp": 1795.7999999821186,
        "lcp": 1795.7999999821186
      }
    ],
    "totalDuration": 152057.03605,
    "setupDuration": 6603.444192999974,
    "diagnosticsDuration": 69.70641799992882,
    "measurementDuration": 135380.75152700022,
    "hasErrors": false,
    "errorCount": 0,
    "errors": []
  },
  {
    "toolName": "Localxpose",
    "measurementNumber": 10,
    "timestamp": 2034680.656753,
    "fileTransfers": [
      {
        "filename": "A_1MB.bin",
        "timestamp": 2034680.660035,
        "fileSize": 1048576,
        "contentType": "application/octet-stream",
        "transferSuccess": true,
        "statusCode": 200,
        "downloadSpeed": 50070,
        "uploadSpeed": 0,
        "dnsLookup": 3.455,
        "tcpConnection": 193.74099999999999,
        "tlsHandshake": 0,
        "timeToFirstByte": 1386.5559999999998,
        "totalTransferTime": 1796.154,
        "hashMatch": false,
        "sizeMatch": false
      },
      {
        "filename": "random_25MB.bin",
        "timestamp": 2036490.523178,
        "fileSize": 26214400,
        "contentType": "application/octet-stream",
        "transferSuccess": true,
        "statusCode": 200,
        "downloadSpeed": 46527,
        "uploadSpeed": 0,
        "dnsLookup": 10.654,
        "tcpConnection": 210.31,
        "tlsHandshake": 0,
        "timeToFirstByte": 1520.6409999999998,
        "totalTransferTime": 1932.9579999999999,
        "hashMatch": false,
        "sizeMatch": false
      }
    ],
    "webTests": [
      {
        "url": "http://eb5gynrvuw.loclx.io/webtest",
        "statusCode": 200,
        "downloadSpeed": 49147,
        "uploadSpeed": 0,
        "dnsLookup": 5.548,
        "tcpConnection": 210.876,
        "tlsHandshake": 0,
        "timeToFirstByte": 1415.449,
        "totalTime": 1829.917,
        "fcp": 1817.0999999940395,
        "lcp": 1817.0999999940395
      }
    ],
    "totalDuration": 152057.03605,
    "setupDuration": 6603.444192999974,
    "diagnosticsDuration": 69.70641799992882,
    "measurementDuration": 135380.75152700022,
    "hasErrors": false,
    "errorCount": 0,
    "errors": []
  },
  {
    "toolName": "Localxpose",
    "measurementNumber": 11,
    "timestamp": 2043282.281468,
    "fileTransfers": [
      {
        "filename": "A_1MB.bin",
        "timestamp": 2043282.285379,
        "fileSize": 1048576,
        "contentType": "application/octet-stream",
        "transferSuccess": true,
        "statusCode": 200,
        "downloadSpeed": 40841,
        "uploadSpeed": 0,
        "dnsLookup": 2.28,
        "tcpConnection": 256.248,
        "tlsHandshake": 0,
        "timeToFirstByte": 1477.2069999999999,
        "totalTransferTime": 2202.057,
        "hashMatch": false,
        "sizeMatch": false
      },
      {
        "filename": "random_25MB.bin",
        "timestamp": 2045498.575965,
        "fileSize": 26214400,
        "contentType": "application/octet-stream",
        "transferSuccess": true,
        "statusCode": 200,
        "downloadSpeed": 51923,
        "uploadSpeed": 0,
        "dnsLookup": 7.409,
        "tcpConnection": 195.894,
        "tlsHandshake": 0,
        "timeToFirstByte": 1318.1670000000001,
        "totalTransferTime": 1732.067,
        "hashMatch": false,
        "sizeMatch": false
      }
    ],
    "webTests": [
      {
        "url": "http://eb5gynrvuw.loclx.io/webtest",
        "statusCode": 200,
        "downloadSpeed": 38455,
        "uploadSpeed": 0,
        "dnsLookup": 9.689,
        "tcpConnection": 211.60000000000002,
        "tlsHandshake": 0,
        "timeToFirstByte": 1513.6080000000002,
        "totalTime": 2338.688,
        "fcp": 1824.7000000178814,
        "lcp": 1824.7000000178814
      }
    ],
    "totalDuration": 152057.03605,
    "setupDuration": 6603.444192999974,
    "diagnosticsDuration": 69.70641799992882,
    "measurementDuration": 135380.75152700022,
    "hasErrors": false,
    "errorCount": 0,
    "errors": []
  },
  {
    "toolName": "Localxpose",
    "measurementNumber": 12,
    "timestamp": 2052492.199795,
    "fileTransfers": [
      {
        "filename": "A_1MB.bin",
        "timestamp": 2052492.202728,
        "fileSize": 1048576,
        "contentType": "application/octet-stream",
        "transferSuccess": true,
        "statusCode": 200,
        "downloadSpeed": 48131,
        "uploadSpeed": 0,
        "dnsLookup": 4.507,
        "tcpConnection": 194.051,
        "tlsHandshake": 0,
        "timeToFirstByte": 1481.579,
        "totalTransferTime": 1868.5130000000001,
        "hashMatch": false,
        "sizeMatch": false
      },
      {
        "filename": "random_25MB.bin",
        "timestamp": 2054374.710023,
        "fileSize": 26214400,
        "contentType": "application/octet-stream",
        "transferSuccess": true,
        "statusCode": 200,
        "downloadSpeed": 41438,
        "uploadSpeed": 0,
        "dnsLookup": 3.371,
        "tcpConnection": 224.00900000000001,
        "tlsHandshake": 0,
        "timeToFirstByte": 1432.344,
        "totalTransferTime": 2170.3489999999997,
        "hashMatch": false,
        "sizeMatch": false
      }
    ],
    "webTests": [
      {
        "url": "http://eb5gynrvuw.loclx.io/webtest",
        "statusCode": 200,
        "downloadSpeed": 46873,
        "uploadSpeed": 0,
        "dnsLookup": 15.514999999999999,
        "tcpConnection": 203.22799999999998,
        "tlsHandshake": 0,
        "timeToFirstByte": 1341.3090000000002,
        "totalTime": 1918.671,
        "fcp": 2078.600000023842,
        "lcp": 2078.600000023842
      }
    ],
    "totalDuration": 152057.03605,
    "setupDuration": 6603.444192999974,
    "diagnosticsDuration": 69.70641799992882,
    "measurementDuration": 135380.75152700022,
    "hasErrors": false,
    "errorCount": 0,
    "errors": []
  },
  {
    "toolName": "Localxpose",
    "measurementNumber": 13,
    "timestamp": 2061451.719525,
    "fileTransfers": [
      {
        "filename": "A_1MB.bin",
        "timestamp": 2061451.722877,
        "fileSize": 1048576,
        "contentType": "application/octet-stream",
        "transferSuccess": true,
        "statusCode": 200,
        "downloadSpeed": 45910,
        "uploadSpeed": 0,
        "dnsLookup": 2.974,
        "tcpConnection": 206.224,
        "tlsHandshake": 0,
        "timeToFirstByte": 1481.057,
        "totalTransferTime": 1958.899,
        "hashMatch": false,
        "sizeMatch": false
      },
      {
        "filename": "random_25MB.bin",
        "timestamp": 2063423.354004,
        "fileSize": 26214400,
        "contentType": "application/octet-stream",
        "transferSuccess": true,
        "statusCode": 200,
        "downloadSpeed": 40263,
        "uploadSpeed": 0,
        "dnsLookup": 3.229,
        "tcpConnection": 288.041,
        "tlsHandshake": 0,
        "timeToFirstByte": 1525.616,
        "totalTransferTime": 2233.682,
        "hashMatch": false,
        "sizeMatch": false
      }
    ],
    "webTests": [
      {
        "url": "http://eb5gynrvuw.loclx.io/webtest",
        "statusCode": 200,
        "downloadSpeed": 40075,
        "uploadSpeed": 0,
        "dnsLookup": 3.476,
        "tcpConnection": 209.173,
        "tlsHandshake": 0,
        "timeToFirstByte": 1420.753,
        "totalTime": 2244.132,
        "fcp": 1921.5999999940395,
        "lcp": 1921.5999999940395
      }
    ],
    "totalDuration": 152057.03605,
    "setupDuration": 6603.444192999974,
    "diagnosticsDuration": 69.70641799992882,
    "measurementDuration": 135380.75152700022,
    "hasErrors": false,
    "errorCount": 0,
    "errors": []
  },
  {
    "toolName": "Localxpose",
    "measurementNumber": 14,
    "timestamp": 2070931.282051,
    "fileTransfers": [
      {
        "filename": "A_1MB.bin",
        "timestamp": 2070931.284915,
        "fileSize": 1048576,
        "contentType": "application/octet-stream",
        "transferSuccess": true,
        "statusCode": 200,
        "downloadSpeed": 50083,
        "uploadSpeed": 0,
        "dnsLookup": 2.5669999999999997,
        "tcpConnection": 197.413,
        "tlsHandshake": 0,
        "timeToFirstByte": 1395.98,
        "totalTransferTime": 1795.692,
        "hashMatch": false,
        "sizeMatch": false
      },
      {
        "filename": "random_25MB.bin",
        "timestamp": 2072740.349702,
        "fileSize": 26214400,
        "contentType": "application/octet-stream",
        "transferSuccess": true,
        "statusCode": 200,
        "downloadSpeed": 49119,
        "uploadSpeed": 0,
        "dnsLookup": 2.913,
        "tcpConnection": 193.434,
        "tlsHandshake": 0,
        "timeToFirstByte": 1416.254,
        "totalTransferTime": 1830.934,
        "hashMatch": false,
        "sizeMatch": false
      }
    ],
    "webTests": [
      {
        "url": "http://eb5gynrvuw.loclx.io/webtest",
        "statusCode": 200,
        "downloadSpeed": 42016,
        "uploadSpeed": 0,
        "dnsLookup": 3.335,
        "tcpConnection": 211.755,
        "tlsHandshake": 0,
        "timeToFirstByte": 1424.231,
        "totalTime": 2140.48,
        "fcp": 1926.199999988079,
        "lcp": 1926.199999988079
      }
    ],
    "totalDuration": 152057.03605,
    "setupDuration": 6603.444192999974,
    "diagnosticsDuration": 69.70641799992882,
    "measurementDuration": 135380.75152700022,
    "hasErrors": false,
    "errorCount": 0,
    "errors": []
  },
  {
    "toolName": "Localxpose",
    "measurementNumber": 15,
    "timestamp": 2079728.793823,
    "fileTransfers": [
      {
        "filename": "A_1MB.bin",
        "timestamp": 2079728.796617,
        "fileSize": 1048576,
        "contentType": "application/octet-stream",
        "transferSuccess": true,
        "statusCode": 200,
        "downloadSpeed": 42644,
        "uploadSpeed": 0,
        "dnsLookup": 2.679,
        "tcpConnection": 191.806,
        "tlsHandshake": 0,
        "timeToFirstByte": 1496.845,
        "totalTransferTime": 2108.946,
        "hashMatch": false,
        "sizeMatch": false
      },
      {
        "filename": "random_25MB.bin",
        "timestamp": 2081850.349109,
        "fileSize": 26214400,
        "contentType": "application/octet-stream",
        "transferSuccess": true,
        "statusCode": 200,
        "downloadSpeed": 48788,
        "uploadSpeed": 0,
        "dnsLookup": 3.454,
        "tcpConnection": 193.28699999999998,
        "tlsHandshake": 0,
        "timeToFirstByte": 1454.157,
        "totalTransferTime": 1843.361,
        "hashMatch": false,
        "sizeMatch": false
      }
    ],
    "webTests": [
      {
        "url": "http://eb5gynrvuw.loclx.io/webtest",
        "statusCode": 200,
        "downloadSpeed": 49323,
        "uploadSpeed": 0,
        "dnsLookup": 3.0300000000000002,
        "tcpConnection": 281.53099999999995,
        "tlsHandshake": 0,
        "timeToFirstByte": 1397.326,
        "totalTime": 1823.3539999999998,
        "fcp": 1930,
        "lcp": 1930
      }
    ],
    "totalDuration": 152057.03605,
    "setupDuration": 6603.444192999974,
    "diagnosticsDuration": 69.70641799992882,
    "measurementDuration": 135380.75152700022,
    "hasErrors": false,
    "errorCount": 0,
    "errors": []
  }
]