[
  {
    "toolName": "Expose",
    "measurementNumber": 1,
    "timestamp": 2865073.4967629984,
    "fileTransfers": [
      {
        "filename": "10MB.txt",
        "timestamp": 2865073.5028439984,
        "fileSize": 10485760,
        "contentType": "text/plain",
        "transferSuccess": true,
        "statusCode": 200,
        "downloadSpeed": 2054010,
        "uploadSpeed": 0,
        "dnsLookup": 75.852,
        "tcpConnection": 231.293,
        "tlsHandshake": 393.237,
        "timeToFirstByte": 2073.845,
        "totalTransferTime": 5105.017,
        "hashMatch": true,
        "sizeMatch": true
      },
      {
        "filename": "1MB.txt",
        "timestamp": 2870211.828125,
        "fileSize": 1048576,
        "contentType": "text/plain",
        "transferSuccess": true,
        "statusCode": 200,
        "downloadSpeed": 363520,
        "uploadSpeed": 0,
        "dnsLookup": 17.96,
        "tcpConnection": 174.16400000000002,
        "tlsHandshake": 341.05,
        "timeToFirstByte": 1936.266,
        "totalTransferTime": 2884.502,
        "hashMatch": true,
        "sizeMatch": true
      },
      {
        "filename": "25MB.txt",
        "timestamp": 2873112.4504849985,
        "fileSize": 26214400,
        "contentType": "text/plain",
        "transferSuccess": true,
        "statusCode": 200,
        "downloadSpeed": 83370,
        "uploadSpeed": 0,
        "dnsLookup": 99.198,
        "tcpConnection": 250.985,
        "tlsHandshake": 412.866,
        "timeToFirstByte": 2124.666,
        "totalTransferTime": 3144.325,
        "hashMatch": false,
        "sizeMatch": false
      }
    ],
    "webTests": [
      {
        "url": "https://yibdgdagus.sharedwithexpose.com/webtest",
        "statusCode": 404,
        "downloadSpeed": 1584,
        "uploadSpeed": 0,
        "dnsLookup": 391.60699999999997,
        "tcpConnection": 809.279,
        "tlsHandshake": 1222.637,
        "timeToFirstByte": 1422.9160000000002,
        "totalTime": 1422.97,
        "fcp": 2608.2999999970198,
        "lcp": 2608.2999999970198
      }
    ],
    "totalDuration": 91171.89669000357,
    "setupDuration": 1633.4662429988384,
    "diagnosticsDuration": 104.59483399987221,
    "measurementDuration": 79431.62739501148,
    "hasErrors": false,
    "errorCount": 0,
    "errors": []
  },
  {
    "toolName": "Expose",
    "measurementNumber": 2,
    "timestamp": 2880792.884804994,
    "fileTransfers": [
      {
        "filename": "10MB.txt",
        "timestamp": 2880792.889082998,
        "fileSize": 10485760,
        "contentType": "text/plain",
        "transferSuccess": false,
        "statusCode": 404,
        "downloadSpeed": 2382,
        "uploadSpeed": 0,
        "dnsLookup": 25.173000000000002,
        "tcpConnection": 383.884,
        "tlsHandshake": 794.7520000000001,
        "timeToFirstByte": 945.652,
        "totalTransferTime": 946.097,
        "hashMatch": false,
        "sizeMatch": false
      },
      {
        "filename": "1MB.txt",
        "timestamp": 2881749.424617,
        "fileSize": 1048576,
        "contentType": "text/plain",
        "transferSuccess": false,
        "statusCode": 404,
        "downloadSpeed": 4321,
        "uploadSpeed": 0,
        "dnsLookup": 19.339,
        "tcpConnection": 180.665,
        "tlsHandshake": 353.833,
        "timeToFirstByte": 521.127,
        "totalTransferTime": 521.5600000000001,
        "hashMatch": false,
        "sizeMatch": false
      },
      {
        "filename": "25MB.txt",
        "timestamp": 2882285.2487239987,
        "fileSize": 26214400,
        "contentType": "text/plain",
        "transferSuccess": false,
        "statusCode": 404,
        "downloadSpeed": 4387,
        "uploadSpeed": 0,
        "dnsLookup": 20.955000000000002,
        "tcpConnection": 179.228,
        "tlsHandshake": 348.49,
        "timeToFirstByte": 513.156,
        "totalTransferTime": 513.693,
        "hashMatch": false,
        "sizeMatch": false
      }
    ],
    "webTests": [
      {
        "url": "https://yibdgdagus.sharedwithexpose.com/webtest",
        "statusCode": 404,
        "downloadSpeed": 4707,
        "uploadSpeed": 0,
        "dnsLookup": 17.872,
        "tcpConnection": 166.056,
        "tlsHandshake": 326.177,
        "timeToFirstByte": 478.343,
        "totalTime": 478.82000000000005,
        "fcp": 2724.60000000149,
        "lcp": 2724.60000000149
      }
    ],
    "totalDuration": 91171.89669000357,
    "setupDuration": 1633.4662429988384,
    "diagnosticsDuration": 104.59483399987221,
    "measurementDuration": 79431.62739501148,
    "hasErrors": false,
    "errorCount": 0,
    "errors": []
  },
  {
    "toolName": "Expose",
    "measurementNumber": 3,
    "timestamp": 2886209.027486995,
    "fileTransfers": [
      {
        "filename": "10MB.txt",
        "timestamp": 2886209.029694997,
        "fileSize": 10485760,
        "contentType": "text/plain",
        "transferSuccess": false,
        "statusCode": 404,
        "downloadSpeed": 1433,
        "uploadSpeed": 0,
        "dnsLookup": 696.842,
        "tcpConnection": 1117.04,
        "tlsHandshake": 1409.208,
        "timeToFirstByte": 1572.027,
        "totalTransferTime": 1572.421,
        "hashMatch": false,
        "sizeMatch": false
      },
      {
        "filename": "1MB.txt",
        "timestamp": 2887795.0367750004,
        "fileSize": 1048576,
        "contentType": "text/plain",
        "transferSuccess": false,
        "statusCode": 404,
        "downloadSpeed": 4452,
        "uploadSpeed": 0,
        "dnsLookup": 26.069,
        "tcpConnection": 180.013,
        "tlsHandshake": 345.777,
        "timeToFirstByte": 505.996,
        "totalTransferTime": 506.224,
        "hashMatch": false,
        "sizeMatch": false
      },
      {
        "filename": "25MB.txt",
        "timestamp": 2888317.724124998,
        "fileSize": 26214400,
        "contentType": "text/plain",
        "transferSuccess": false,
        "statusCode": 404,
        "downloadSpeed": 4285,
        "uploadSpeed": 0,
        "dnsLookup": 18,
        "tcpConnection": 181.425,
        "tlsHandshake": 356.21000000000004,
        "timeToFirstByte": 525.557,
        "totalTransferTime": 526.015,
        "hashMatch": false,
        "sizeMatch": false
      }
    ],
    "webTests": [
      {
        "url": "https://yibdgdagus.sharedwithexpose.com/webtest",
        "statusCode": 404,
        "downloadSpeed": 4515,
        "uploadSpeed": 0,
        "dnsLookup": 23.695,
        "tcpConnection": 176.09,
        "tlsHandshake": 339.849,
        "timeToFirstByte": 498.877,
        "totalTime": 499.142,
        "fcp": 2074.89999999851,
        "lcp": 2074.89999999851
      }
    ],
    "totalDuration": 91171.89669000357,
    "setupDuration": 1633.4662429988384,
    "diagnosticsDuration": 104.59483399987221,
    "measurementDuration": 79431.62739501148,
    "hasErrors": false,
    "errorCount": 0,
    "errors": []
  },
  {
    "toolName": "Expose",
    "measurementNumber": 4,
    "timestamp": 2891624.602226995,
    "fileTransfers": [
      {
        "filename": "10MB.txt",
        "timestamp": 2891624.6053379998,
        "fileSize": 10485760,
        "contentType": "text/plain",
        "transferSuccess": false,
        "statusCode": 404,
        "downloadSpeed": 4154,
        "uploadSpeed": 0,
        "dnsLookup": 39.186,
        "tcpConnection": 201.11499999999998,
        "tlsHandshake": 374.536,
        "timeToFirstByte": 541.946,
        "totalTransferTime": 542.528,
        "hashMatch": false,
        "sizeMatch": false
      },
      {
        "filename": "1MB.txt",
        "timestamp": 2892178.0315599963,
        "fileSize": 1048576,
        "contentType": "text/plain",
        "transferSuccess": false,
        "statusCode": 404,
        "downloadSpeed": 4200,
        "uploadSpeed": 0,
        "dnsLookup": 20.555,
        "tcpConnection": 186.568,
        "tlsHandshake": 364.644,
        "timeToFirstByte": 536.193,
        "totalTransferTime": 536.593,
        "hashMatch": false,
        "sizeMatch": false
      },
      {
        "filename": "25MB.txt",
        "timestamp": 2892726.868083,
        "fileSize": 26214400,
        "contentType": "text/plain",
        "transferSuccess": false,
        "statusCode": 404,
        "downloadSpeed": 4557,
        "uploadSpeed": 0,
        "dnsLookup": 18.504,
        "tcpConnection": 171.566,
        "tlsHandshake": 335.37899999999996,
        "timeToFirstByte": 494.398,
        "totalTransferTime": 494.588,
        "hashMatch": false,
        "sizeMatch": false
      }
    ],
    "webTests": [
      {
        "url": "https://yibdgdagus.sharedwithexpose.com/webtest",
        "statusCode": 404,
        "downloadSpeed": 3556,
        "uploadSpeed": 0,
        "dnsLookup": 19.809,
        "tcpConnection": 169.181,
        "tlsHandshake": 326.923,
        "timeToFirstByte": 633.654,
        "totalTime": 633.71,
        "fcp": 2223.5,
        "lcp": 2223.5
      }
    ],
    "totalDuration": 91171.89669000357,
    "setupDuration": 1633.4662429988384,
    "diagnosticsDuration": 104.59483399987221,
    "measurementDuration": 79431.62739501148,
    "hasErrors": false,
    "errorCount": 0,
    "errors": []
  },
  {
    "toolName": "Expose",
    "measurementNumber": 5,
    "timestamp": 2896374.9056859985,
    "fileTransfers": [
      {
        "filename": "10MB.txt",
        "timestamp": 2896374.9106179997,
        "fileSize": 10485760,
        "contentType": "text/plain",
        "transferSuccess": false,
        "statusCode": 404,
        "downloadSpeed": 1895,
        "uploadSpeed": 0,
        "dnsLookup": 16.768,
        "tcpConnection": 364.93199999999996,
        "tlsHandshake": 782.198,
        "timeToFirstByte": 1189.039,
        "totalTransferTime": 1189.185,
        "hashMatch": false,
        "sizeMatch": false
      },
      {
        "filename": "1MB.txt",
        "timestamp": 2897577.4164179936,
        "fileSize": 1048576,
        "contentType": "text/plain",
        "transferSuccess": false,
        "statusCode": 404,
        "downloadSpeed": 4144,
        "uploadSpeed": 0,
        "dnsLookup": 78.308,
        "tcpConnection": 230.30200000000002,
        "tlsHandshake": 387.48,
        "timeToFirstByte": 543.4780000000001,
        "totalTransferTime": 543.861,
        "hashMatch": false,
        "sizeMatch": false
      },
      {
        "filename": "25MB.txt",
        "timestamp": 2898137.4968239963,
        "fileSize": 26214400,
        "contentType": "text/plain",
        "transferSuccess": false,
        "statusCode": 404,
        "downloadSpeed": 4412,
        "uploadSpeed": 0,
        "dnsLookup": 19.176,
        "tcpConnection": 177.458,
        "tlsHandshake": 344.97,
        "timeToFirstByte": 510.093,
        "totalTransferTime": 510.853,
        "hashMatch": false,
        "sizeMatch": false
      }
    ],
    "webTests": [
      {
        "url": "https://yibdgdagus.sharedwithexpose.com/webtest",
        "statusCode": 404,
        "downloadSpeed": 4205,
        "uploadSpeed": 0,
        "dnsLookup": 17.776,
        "tcpConnection": 185.834,
        "tlsHandshake": 363.40099999999995,
        "timeToFirstByte": 535.004,
        "totalTime": 535.956,
        "fcp": 1128.3000000044703,
        "lcp": 1128.3000000044703
      }
    ],
    "totalDuration": 91171.89669000357,
    "setupDuration": 1633.4662429988384,
    "diagnosticsDuration": 104.59483399987221,
    "measurementDuration": 79431.62739501148,
    "hasErrors": false,
    "errorCount": 0,
    "errors": []
  },
  {
    "toolName": "Expose",
    "measurementNumber": 6,
    "timestamp": 2900492.689527996,
    "fileTransfers": [
      {
        "filename": "10MB.txt",
        "timestamp": 2900492.692808993,
        "fileSize": 10485760,
        "contentType": "text/plain",
        "transferSuccess": false,
        "statusCode": 404,
        "downloadSpeed": 4658,
        "uploadSpeed": 0,
        "dnsLookup": 18.783,
        "tcpConnection": 167.128,
        "tlsHandshake": 323.667,
        "timeToFirstByte": 483.361,
        "totalTransferTime": 483.822,
        "hashMatch": false,
        "sizeMatch": false
      },
      {
        "filename": "1MB.txt",
        "timestamp": 2900987.070827,
        "fileSize": 1048576,
        "contentType": "text/plain",
        "transferSuccess": false,
        "statusCode": 404,
        "downloadSpeed": 4726,
        "uploadSpeed": 0,
        "dnsLookup": 19.465,
        "tcpConnection": 166.79,
        "tlsHandshake": 320.394,
        "timeToFirstByte": 476.089,
        "totalTransferTime": 476.928,
        "hashMatch": false,
        "sizeMatch": false
      },
      {
        "filename": "25MB.txt",
        "timestamp": 2901476.130664997,
        "fileSize": 26214400,
        "contentType": "text/plain",
        "transferSuccess": false,
        "statusCode": 404,
        "downloadSpeed": 4599,
        "uploadSpeed": 0,
        "dnsLookup": 17.999000000000002,
        "tcpConnection": 169.935,
        "tlsHandshake": 331.338,
        "timeToFirstByte": 489.63,
        "totalTransferTime": 490.02099999999996,
        "hashMatch": false,
        "sizeMatch": false
      }
    ],
    "webTests": [
      {
        "url": "https://yibdgdagus.sharedwithexpose.com/webtest",
        "statusCode": 404,
        "downloadSpeed": 4711,
        "uploadSpeed": 0,
        "dnsLookup": 17.291,
        "tcpConnection": 165.546,
        "tlsHandshake": 321.957,
        "timeToFirstByte": 478.236,
        "totalTime": 478.37800000000004,
        "fcp": 1093.7000000029802,
        "lcp": 1093.7000000029802
      }
    ],
    "totalDuration": 91171.89669000357,
    "setupDuration": 1633.4662429988384,
    "diagnosticsDuration": 104.59483399987221,
    "measurementDuration": 79431.62739501148,
    "hasErrors": false,
    "errorCount": 0,
    "errors": []
  },
  {
    "toolName": "Expose",
    "measurementNumber": 7,
    "timestamp": 2903708.344310999,
    "fileTransfers": [
      {
        "filename": "10MB.txt",
        "timestamp": 2903708.347071998,
        "fileSize": 10485760,
        "contentType": "text/plain",
        "transferSuccess": false,
        "statusCode": 404,
        "downloadSpeed": 4675,
        "uploadSpeed": 0,
        "dnsLookup": 17.132,
        "tcpConnection": 167.28199999999998,
        "tlsHandshake": 322.759,
        "timeToFirstByte": 482.02099999999996,
        "totalTransferTime": 482.133,
        "hashMatch": false,
        "sizeMatch": false
      },
      {
        "filename": "1MB.txt",
        "timestamp": 2904200.157918997,
        "fileSize": 1048576,
        "contentType": "text/plain",
        "transferSuccess": false,
        "statusCode": 404,
        "downloadSpeed": 4448,
        "uploadSpeed": 0,
        "dnsLookup": 18.064,
        "tcpConnection": 175.47899999999998,
        "tlsHandshake": 343.358,
        "timeToFirstByte": 506.2950000000001,
        "totalTransferTime": 506.686,
        "hashMatch": false,
        "sizeMatch": false
      },
      {
        "filename": "25MB.txt",
        "timestamp": 2904717.3385449946,
        "fileSize": 26214400,
        "contentType": "text/plain",
        "transferSuccess": false,
        "statusCode": 404,
        "downloadSpeed": 4771,
        "uploadSpeed": 0,
        "dnsLookup": 19.349,
        "tcpConnection": 165.322,
        "tlsHandshake": 319.43100000000004,
        "timeToFirstByte": 472.188,
        "totalTransferTime": 472.429,
        "hashMatch": false,
        "sizeMatch": false
      }
    ],
    "webTests": [
      {
        "url": "https://yibdgdagus.sharedwithexpose.com/webtest",
        "statusCode": 404,
        "downloadSpeed": 4046,
        "uploadSpeed": 0,
        "dnsLookup": 17.868,
        "tcpConnection": 171.177,
        "tlsHandshake": 330.06600000000003,
        "timeToFirstByte": 556.935,
        "totalTime": 557.028,
        "fcp": 1722.8999999985099,
        "lcp": 1722.8999999985099
      }
    ],
    "totalDuration": 91171.89669000357,
    "setupDuration": 1633.4662429988384,
    "diagnosticsDuration": 104.59483399987221,
    "measurementDuration": 79431.62739501148,
    "hasErrors": false,
    "errorCount": 0,
    "errors": []
  },
  {
    "toolName": "Expose",
    "measurementNumber": 8,
    "timestamp": 2907690.5298499987,
    "fileTransfers": [
      {
        "filename": "10MB.txt",
        "timestamp": 2907690.534320995,
        "fileSize": 10485760,
        "contentType": "text/plain",
        "transferSuccess": false,
        "statusCode": 404,
        "downloadSpeed": 4317,
        "uploadSpeed": 0,
        "dnsLookup": 18.964000000000002,
        "tcpConnection": 180.392,
        "tlsHandshake": 350.798,
        "timeToFirstByte": 521.959,
        "totalTransferTime": 522.115,
        "hashMatch": false,
        "sizeMatch": false
      },
      {
        "filename": "1MB.txt",
        "timestamp": 2908227.877733998,
        "fileSize": 1048576,
        "contentType": "text/plain",
        "transferSuccess": false,
        "statusCode": 404,
        "downloadSpeed": 4493,
        "uploadSpeed": 0,
        "dnsLookup": 17.744,
        "tcpConnection": 173.55,
        "tlsHandshake": 335.814,
        "timeToFirstByte": 501.037,
        "totalTransferTime": 501.563,
        "hashMatch": false,
        "sizeMatch": false
      },
      {
        "filename": "25MB.txt",
        "timestamp": 2908746.112020999,
        "fileSize": 26214400,
        "contentType": "text/plain",
        "transferSuccess": false,
        "statusCode": 404,
        "downloadSpeed": 4765,
        "uploadSpeed": 0,
        "dnsLookup": 18.268,
        "tcpConnection": 164.213,
        "tlsHandshake": 320.413,
        "timeToFirstByte": 472.041,
        "totalTransferTime": 472.98400000000004,
        "hashMatch": false,
        "sizeMatch": false
      }
    ],
    "webTests": [
      {
        "url": "https://yibdgdagus.sharedwithexpose.com/webtest",
        "statusCode": 404,
        "downloadSpeed": 3661,
        "uploadSpeed": 0,
        "dnsLookup": 19.759999999999998,
        "tcpConnection": 178.531,
        "tlsHandshake": 342.82800000000003,
        "timeToFirstByte": 615.529,
        "totalTime": 615.572,
        "fcp": 2399.5999999940395,
        "lcp": 2399.5999999940395
      }
    ],
    "totalDuration": 91171.89669000357,
    "setupDuration": 1633.4662429988384,
    "diagnosticsDuration": 104.59483399987221,
    "measurementDuration": 79431.62739501148,
    "hasErrors": false,
    "errorCount": 0,
    "errors": []
  },
  {
    "toolName": "Expose",
    "measurementNumber": 9,
    "timestamp": 2912428.224013999,
    "fileTransfers": [
      {
        "filename": "10MB.txt",
        "timestamp": 2912428.2262849957,
        "fileSize": 10485760,
        "contentType": "text/plain",
        "transferSuccess": false,
        "statusCode": 404,
        "downloadSpeed": 1761,
        "uploadSpeed": 0,
        "dnsLookup": 304.387,
        "tcpConnection": 701.774,
        "tlsHandshake": 1113.93,
        "timeToFirstByte": 1279.3129999999999,
        "totalTransferTime": 1279.679,
        "hashMatch": false,
        "sizeMatch": false
      },
      {
        "filename": "1MB.txt",
        "timestamp": 2913720.6597059965,
        "fileSize": 1048576,
        "contentType": "text/plain",
        "transferSuccess": false,
        "statusCode": 404,
        "downloadSpeed": 4431,
        "uploadSpeed": 0,
        "dnsLookup": 19.241,
        "tcpConnection": 173.632,
        "tlsHandshake": 347.978,
        "timeToFirstByte": 507.71,
        "totalTransferTime": 508.603,
        "hashMatch": false,
        "sizeMatch": false
      },
      {
        "filename": "25MB.txt",
        "timestamp": 2914244.521410994,
        "fileSize": 26214400,
        "contentType": "text/plain",
        "transferSuccess": false,
        "statusCode": 404,
        "downloadSpeed": 3747,
        "uploadSpeed": 0,
        "dnsLookup": 93.806,
        "tcpConnection": 257.347,
        "tlsHandshake": 431.581,
        "timeToFirstByte": 601.124,
        "totalTransferTime": 601.463,
        "hashMatch": false,
        "sizeMatch": false
      }
    ],
    "webTests": [
      {
        "url": "https://yibdgdagus.sharedwithexpose.com/webtest",
        "statusCode": 404,
        "downloadSpeed": 4577,
        "uploadSpeed": 0,
        "dnsLookup": 19.198,
        "tcpConnection": 170.25799999999998,
        "tlsHandshake": 332.584,
        "timeToFirstByte": 491.29,
        "totalTime": 492.462,
        "fcp": 1550.8000000044703,
        "lcp": 1550.8000000044703
      }
    ],
    "totalDuration": 91171.89669000357,
    "setupDuration": 1633.4662429988384,
    "diagnosticsDuration": 104.59483399987221,
    "measurementDuration": 79431.62739501148,
    "hasErrors": false,
    "errorCount": 0,
    "errors": []
  },
  {
    "toolName": "Expose",
    "measurementNumber": 10,
    "timestamp": 2917264.2437479943,
    "fileTransfers": [
      {
        "filename": "10MB.txt",
        "timestamp": 2917264.2488309965,
        "fileSize": 10485760,
        "contentType": "text/plain",
        "transferSuccess": false,
        "statusCode": 404,
        "downloadSpeed": 2381,
        "uploadSpeed": 0,
        "dnsLookup": 466.113,
        "tcpConnection": 621.201,
        "tlsHandshake": 785.428,
        "timeToFirstByte": 945.932,
        "totalTransferTime": 946.644,
        "hashMatch": false,
        "sizeMatch": false
      },
      {
        "filename": "1MB.txt",
        "timestamp": 2918226.0179799944,
        "fileSize": 1048576,
        "contentType": "text/plain",
        "transferSuccess": false,
        "statusCode": 404,
        "downloadSpeed": 4478,
        "uploadSpeed": 0,
        "dnsLookup": 17.343999999999998,
        "tcpConnection": 173.048,
        "tlsHandshake": 340.52,
        "timeToFirstByte": 502.309,
        "totalTransferTime": 503.323,
        "hashMatch": false,
        "sizeMatch": false
      },
      {
        "filename": "25MB.txt",
        "timestamp": 2918745.906260997,
        "fileSize": 26214400,
        "contentType": "text/plain",
        "transferSuccess": false,
        "statusCode": 404,
        "downloadSpeed": 4404,
        "uploadSpeed": 0,
        "dnsLookup": 18.392,
        "tcpConnection": 182.135,
        "tlsHandshake": 346.439,
        "timeToFirstByte": 511.366,
        "totalTransferTime": 511.726,
        "hashMatch": false,
        "sizeMatch": false
      }
    ],
    "webTests": [
      {
        "url": "https://yibdgdagus.sharedwithexpose.com/webtest",
        "statusCode": 404,
        "downloadSpeed": 4689,
        "uploadSpeed": 0,
        "dnsLookup": 19.476,
        "tcpConnection": 167.294,
        "tlsHandshake": 324.07399999999996,
        "timeToFirstByte": 480.298,
        "totalTime": 480.678,
        "fcp": 1148.5,
        "lcp": 1148.5
      }
    ],
    "totalDuration": 91171.89669000357,
    "setupDuration": 1633.4662429988384,
    "diagnosticsDuration": 104.59483399987221,
    "measurementDuration": 79431.62739501148,
    "hasErrors": false,
    "errorCount": 0,
    "errors": []
  },
  {
    "toolName": "Expose",
    "measurementNumber": 11,
    "timestamp": 2921096.845294997,
    "fileTransfers": [
      {
        "filename": "10MB.txt",
        "timestamp": 2921096.847225994,
        "fileSize": 10485760,
        "contentType": "text/plain",
        "transferSuccess": false,
        "statusCode": 404,
        "downloadSpeed": 4468,
        "uploadSpeed": 0,
        "dnsLookup": 18.179000000000002,
        "tcpConnection": 174.762,
        "tlsHandshake": 337.806,
        "timeToFirstByte": 504.181,
        "totalTransferTime": 504.38700000000006,
        "hashMatch": false,
        "sizeMatch": false
      },
      {
        "filename": "1MB.txt",
        "timestamp": 2921613.8722929955,
        "fileSize": 1048576,
        "contentType": "text/plain",
        "transferSuccess": false,
        "statusCode": 404,
        "downloadSpeed": 4667,
        "uploadSpeed": 0,
        "dnsLookup": 20.262,
        "tcpConnection": 168.656,
        "tlsHandshake": 324.505,
        "timeToFirstByte": 482.814,
        "totalTransferTime": 482.945,
        "hashMatch": false,
        "sizeMatch": false
      },
      {
        "filename": "25MB.txt",
        "timestamp": 2922112.3743669987,
        "fileSize": 26214400,
        "contentType": "text/plain",
        "transferSuccess": false,
        "statusCode": 404,
        "downloadSpeed": 4510,
        "uploadSpeed": 0,
        "dnsLookup": 17.888,
        "tcpConnection": 173.16899999999998,
        "tlsHandshake": 334.098,
        "timeToFirstByte": 499.31399999999996,
        "totalTransferTime": 499.721,
        "hashMatch": false,
        "sizeMatch": false
      }
    ],
    "webTests": [
      {
        "url": "https://yibdgdagus.sharedwithexpose.com/webtest",
        "statusCode": 404,
        "downloadSpeed": 4178,
        "uploadSpeed": 0,
        "dnsLookup": 17.503,
        "tcpConnection": 186.12699999999998,
        "tlsHandshake": 360.935,
        "timeToFirstByte": 539.003,
        "totalTime": 539.486,
        "fcp": 1491.8999999985099,
        "lcp": 1491.8999999985099
      }
    ],
    "totalDuration": 91171.89669000357,
    "setupDuration": 1633.4662429988384,
    "diagnosticsDuration": 104.59483399987221,
    "measurementDuration": 79431.62739501148,
    "hasErrors": false,
    "errorCount": 0,
    "errors": []
  },
  {
    "toolName": "Expose",
    "measurementNumber": 12,
    "timestamp": 2925031.2724939957,
    "fileTransfers": [
      {
        "filename": "10MB.txt",
        "timestamp": 2925031.2748589963,
        "fileSize": 10485760,
        "contentType": "text/plain",
        "transferSuccess": false,
        "statusCode": 404,
        "downloadSpeed": 2942,
        "uploadSpeed": 0,
        "dnsLookup": 17.455,
        "tcpConnection": 387.001,
        "tlsHandshake": 605.092,
        "timeToFirstByte": 765.015,
        "totalTransferTime": 765.914,
        "hashMatch": false,
        "sizeMatch": false
      },
      {
        "filename": "1MB.txt",
        "timestamp": 2925805.869703993,
        "fileSize": 1048576,
        "contentType": "text/plain",
        "transferSuccess": false,
        "statusCode": 404,
        "downloadSpeed": 4369,
        "uploadSpeed": 0,
        "dnsLookup": 18.543,
        "tcpConnection": 178.357,
        "tlsHandshake": 347.88599999999997,
        "timeToFirstByte": 515.6840000000001,
        "totalTransferTime": 515.861,
        "hashMatch": false,
        "sizeMatch": false
      },
      {
        "filename": "25MB.txt",
        "timestamp": 2926333.4285179973,
        "fileSize": 26214400,
        "contentType": "text/plain",
        "transferSuccess": false,
        "statusCode": 404,
        "downloadSpeed": 4377,
        "uploadSpeed": 0,
        "dnsLookup": 18.464000000000002,
        "tcpConnection": 178.437,
        "tlsHandshake": 348.07500000000005,
        "timeToFirstByte": 514.494,
        "totalTransferTime": 514.957,
        "hashMatch": false,
        "sizeMatch": false
      }
    ],
    "webTests": [
      {
        "url": "https://yibdgdagus.sharedwithexpose.com/webtest",
        "statusCode": 404,
        "downloadSpeed": 4796,
        "uploadSpeed": 0,
        "dnsLookup": 19.273,
        "tcpConnection": 162.94,
        "tlsHandshake": 318.676,
        "timeToFirstByte": 469.79900000000004,
        "totalTime": 469.931,
        "fcp": 2499.7999999970198,
        "lcp": 2499.7999999970198
      }
    ],
    "totalDuration": 91171.89669000357,
    "setupDuration": 1633.4662429988384,
    "diagnosticsDuration": 104.59483399987221,
    "measurementDuration": 79431.62739501148,
    "hasErrors": false,
    "errorCount": 0,
    "errors": []
  },
  {
    "toolName": "Expose",
    "measurementNumber": 13,
    "timestamp": 2930012.457023993,
    "fileTransfers": [
      {
        "filename": "10MB.txt",
        "timestamp": 2930012.4608219936,
        "fileSize": 10485760,
        "contentType": "text/plain",
        "transferSuccess": false,
        "statusCode": 404,
        "downloadSpeed": 4795,
        "uploadSpeed": 0,
        "dnsLookup": 18.781,
        "tcpConnection": 165.716,
        "tlsHandshake": 320.34000000000003,
        "timeToFirstByte": 469.846,
        "totalTransferTime": 470.019,
        "hashMatch": false,
        "sizeMatch": false
      },
      {
        "filename": "1MB.txt",
        "timestamp": 2930494.740653999,
        "fileSize": 1048576,
        "contentType": "text/plain",
        "transferSuccess": false,
        "statusCode": 404,
        "downloadSpeed": 4104,
        "uploadSpeed": 0,
        "dnsLookup": 19.631,
        "tcpConnection": 190.487,
        "tlsHandshake": 368.954,
        "timeToFirstByte": 549.008,
        "totalTransferTime": 549.219,
        "hashMatch": false,
        "sizeMatch": false
      },
      {
        "filename": "25MB.txt",
        "timestamp": 2931059.0957289934,
        "fileSize": 26214400,
        "contentType": "text/plain",
        "transferSuccess": false,
        "statusCode": 404,
        "downloadSpeed": 3177,
        "uploadSpeed": 0,
        "dnsLookup": 100.5,
        "tcpConnection": 269.489,
        "tlsHandshake": 446.898,
        "timeToFirstByte": 709.307,
        "totalTransferTime": 709.469,
        "hashMatch": false,
        "sizeMatch": false
      }
    ],
    "webTests": [
      {
        "url": "https://yibdgdagus.sharedwithexpose.com/webtest",
        "statusCode": 404,
        "downloadSpeed": 1597,
        "uploadSpeed": 0,
        "dnsLookup": 174.162,
        "tcpConnection": 586.982,
        "tlsHandshake": 998.189,
        "timeToFirstByte": 1410.7179999999998,
        "totalTime": 1410.857,
        "fcp": 2404.3000000044703,
        "lcp": 2404.3000000044703
      }
    ],
    "totalDuration": 91171.89669000357,
    "setupDuration": 1633.4662429988384,
    "diagnosticsDuration": 104.59483399987221,
    "measurementDuration": 79431.62739501148,
    "hasErrors": false,
    "errorCount": 0,
    "errors": []
  },
  {
    "toolName": "Expose",
    "measurementNumber": 14,
    "timestamp": 2935789.9814479947,
    "fileTransfers": [
      {
        "filename": "10MB.txt",
        "timestamp": 2935789.983154997,
        "fileSize": 10485760,
        "contentType": "text/plain",
        "transferSuccess": false,
        "statusCode": 404,
        "downloadSpeed": 4711,
        "uploadSpeed": 0,
        "dnsLookup": 19.164,
        "tcpConnection": 166.494,
        "tlsHandshake": 325.45000000000005,
        "timeToFirstByte": 478.136,
        "totalTransferTime": 478.368,
        "hashMatch": false,
        "sizeMatch": false
      },
      {
        "filename": "1MB.txt",
        "timestamp": 2936279.783055,
        "fileSize": 1048576,
        "contentType": "text/plain",
        "transferSuccess": false,
        "statusCode": 404,
        "downloadSpeed": 4227,
        "uploadSpeed": 0,
        "dnsLookup": 18.578,
        "tcpConnection": 183.29000000000002,
        "tlsHandshake": 359.589,
        "timeToFirstByte": 532.6880000000001,
        "totalTransferTime": 533.126,
        "hashMatch": false,
        "sizeMatch": false
      },
      {
        "filename": "25MB.txt",
        "timestamp": 2936828.2612639964,
        "fileSize": 26214400,
        "contentType": "text/plain",
        "transferSuccess": false,
        "statusCode": 404,
        "downloadSpeed": 4203,
        "uploadSpeed": 0,
        "dnsLookup": 17.96,
        "tcpConnection": 185.18599999999998,
        "tlsHandshake": 361.447,
        "timeToFirstByte": 535.5600000000001,
        "totalTransferTime": 536.1709999999999,
        "hashMatch": false,
        "sizeMatch": false
      }
    ],
    "webTests": [
      {
        "url": "https://yibdgdagus.sharedwithexpose.com/webtest",
        "statusCode": 404,
        "downloadSpeed": 3104,
        "uploadSpeed": 0,
        "dnsLookup": 19.223,
        "tcpConnection": 170.24900000000002,
        "tlsHandshake": 524.235,
        "timeToFirstByte": 725.9449999999999,
        "totalTime": 726.009,
        "fcp": 2205.5,
        "lcp": 2205.5
      }
    ],
    "totalDuration": 91171.89669000357,
    "setupDuration": 1633.4662429988384,
    "diagnosticsDuration": 104.59483399987221,
    "measurementDuration": 79431.62739501148,
    "hasErrors": false,
    "errorCount": 0,
    "errors": []
  },
  {
    "toolName": "Expose",
    "measurementNumber": 15,
    "timestamp": 2940616.7994419932,
    "fileTransfers": [
      {
        "filename": "10MB.txt",
        "timestamp": 2940616.8019569963,
        "fileSize": 10485760,
        "contentType": "text/plain",
        "transferSuccess": false,
        "statusCode": 404,
        "downloadSpeed": 2042,
        "uploadSpeed": 0,
        "dnsLookup": 377.753,
        "tcpConnection": 771.616,
        "tlsHandshake": 938.748,
        "timeToFirstByte": 1103.149,
        "totalTransferTime": 1103.2839999999999,
        "hashMatch": false,
        "sizeMatch": false
      },
      {
        "filename": "1MB.txt",
        "timestamp": 2941730.0795409977,
        "fileSize": 1048576,
        "contentType": "text/plain",
        "transferSuccess": false,
        "statusCode": 404,
        "downloadSpeed": 4599,
        "uploadSpeed": 0,
        "dnsLookup": 19.186,
        "tcpConnection": 170.61,
        "tlsHandshake": 328.47900000000004,
        "timeToFirstByte": 489.68600000000004,
        "totalTransferTime": 490.051,
        "hashMatch": false,
        "sizeMatch": false
      },
      {
        "filename": "25MB.txt",
        "timestamp": 2942229.654796995,
        "fileSize": 26214400,
        "contentType": "text/plain",
        "transferSuccess": false,
        "statusCode": 404,
        "downloadSpeed": 4763,
        "uploadSpeed": 0,
        "dnsLookup": 17.796,
        "tcpConnection": 164.267,
        "tlsHandshake": 318.656,
        "timeToFirstByte": 472.983,
        "totalTransferTime": 473.207,
        "hashMatch": false,
        "sizeMatch": false
      }
    ],
    "webTests": [
      {
        "url": "https://yibdgdagus.sharedwithexpose.com/webtest",
        "statusCode": 404,
        "downloadSpeed": 4619,
        "uploadSpeed": 0,
        "dnsLookup": 18.936999999999998,
        "tcpConnection": 169.86499999999998,
        "tlsHandshake": 328.512,
        "timeToFirstByte": 487.822,
        "totalTime": 487.938,
        "fcp": 1110.2999999970198,
        "lcp": 1110.2999999970198
      }
    ],
    "totalDuration": 91171.89669000357,
    "setupDuration": 1633.4662429988384,
    "diagnosticsDuration": 104.59483399987221,
    "measurementDuration": 79431.62739501148,
    "hasErrors": false,
    "errorCount": 0,
    "errors": []
  }
]