[
  {
    "toolName": "Telebit",
    "measurementNumber": 1,
    "timestamp": 3366613.3996890006,
    "fileTransfers": [],
    "webTests": [],
    "totalDuration": 21216.313512000255,
    "setupDuration": 11058.640457999893,
    "diagnosticsDuration": 0.014940999448299408,
    "measurementDuration": 157.1036660009995,
    "hasErrors": true,
    "errorCount": 19,
    "errors": [
      "Tunnel Setup: Failed to start tunnel: Request failed with status code 500",
      "Tunnel Setup: Tunnel URL is empty or invalid",
      "Diagnostics: Skipped diagnostics due to missing tunnel URL",
      "Web Test: Failed to perform web test: Command failed with code 3",
      "Web Test: Failed to perform web test: Command failed with code 3",
      "Web Test: Failed to perform web test: Command failed with code 3",
      "Web Test: Failed to perform web test: Command failed with code 3",
      "Web Test: Failed to perform web test: Command failed with code 3",
      "Web Test: Failed to perform web test: Command failed with code 3",
      "Web Test: Failed to perform web test: Command failed with code 3",
      "Web Test: Failed to perform web test: Command failed with code 3",
      "Web Test: Failed to perform web test: Command failed with code 3",
      "Web Test: Failed to perform web test: Command failed with code 3",
      "Web Test: Failed to perform web test: Command failed with code 3",
      "Web Test: Failed to perform web test: Command failed with code 3",
      "Web Test: Failed to perform web test: Command failed with code 3",
      "Web Test: Failed to perform web test: Command failed with code 3",
      "Web Test: Failed to perform web test: Command failed with code 3",
      "Tunnel Cleanup: Failed to stop tunnel: Request failed with status code 400"
    ]
  },
  {
    "toolName": "Telebit",
    "measurementNumber": 2,
    "timestamp": 3366629.823645,
    "fileTransfers": [],
    "webTests": [],
    "totalDuration": 21216.313512000255,
    "setupDuration": 11058.640457999893,
    "diagnosticsDuration": 0.014940999448299408,
    "measurementDuration": 157.1036660009995,
    "hasErrors": true,
    "errorCount": 19,
    "errors": [
      "Tunnel Setup: Failed to start tunnel: Request failed with status code 500",
      "Tunnel Setup: Tunnel URL is empty or invalid",
      "Diagnostics: Skipped diagnostics due to missing tunnel URL",
      "Web Test: Failed to perform web test: Command failed with code 3",
      "Web Test: Failed to perform web test: Command failed with code 3",
      "Web Test: Failed to perform web test: Command failed with code 3",
      "Web Test: Failed to perform web test: Command failed with code 3",
      "Web Test: Failed to perform web test: Command failed with code 3",
      "Web Test: Failed to perform web test: Command failed with code 3",
      "Web Test: Failed to perform web test: Command failed with code 3",
      "Web Test: Failed to perform web test: Command failed with code 3",
      "Web Test: Failed to perform web test: Command failed with code 3",
      "Web Test: Failed to perform web test: Command failed with code 3",
      "Web Test: Failed to perform web test: Command failed with code 3",
      "Web Test: Failed to perform web test: Command failed with code 3",
      "Web Test: Failed to perform web test: Command failed with code 3",
      "Web Test: Failed to perform web test: Command failed with code 3",
      "Web Test: Failed to perform web test: Command failed with code 3",
      "Tunnel Cleanup: Failed to stop tunnel: Request failed with status code 400"
    ]
  },
  {
    "toolName": "Telebit",
    "measurementNumber": 3,
    "timestamp": 3366645.411179,
    "fileTransfers": [],
    "webTests": [],
    "totalDuration": 21216.313512000255,
    "setupDuration": 11058.640457999893,
    "diagnosticsDuration": 0.014940999448299408,
    "measurementDuration": 157.1036660009995,
    "hasErrors": true,
    "errorCount": 19,
    "errors": [
      "Tunnel Setup: Failed to start tunnel: Request failed with status code 500",
      "Tunnel Setup: Tunnel URL is empty or invalid",
      "Diagnostics: Skipped diagnostics due to missing tunnel URL",
      "Web Test: Failed to perform web test: Command failed with code 3",
      "Web Test: Failed to perform web test: Command failed with code 3",
      "Web Test: Failed to perform web test: Command failed with code 3",
      "Web Test: Failed to perform web test: Command failed with code 3",
      "Web Test: Failed to perform web test: Command failed with code 3",
      "Web Test: Failed to perform web test: Command failed with code 3",
      "Web Test: Failed to perform web test: Command failed with code 3",
      "Web Test: Failed to perform web test: Command failed with code 3",
      "Web Test: Failed to perform web test: Command failed with code 3",
      "Web Test: Failed to perform web test: Command failed with code 3",
      "Web Test: Failed to perform web test: Command failed with code 3",
      "Web Test: Failed to perform web test: Command failed with code 3",
      "Web Test: Failed to perform web test: Command failed with code 3",
      "Web Test: Failed to perform web test: Command failed with code 3",
      "Web Test: Failed to perform web test: Command failed with code 3",
      "Tunnel Cleanup: Failed to stop tunnel: Request failed with status code 400"
    ]
  },
  {
    "toolName": "Telebit",
    "measurementNumber": 4,
    "timestamp": 3366660.4293200006,
    "fileTransfers": [],
    "webTests": [],
    "totalDuration": 21216.313512000255,
    "setupDuration": 11058.640457999893,
    "diagnosticsDuration": 0.014940999448299408,
    "measurementDuration": 157.1036660009995,
    "hasErrors": true,
    "errorCount": 19,
    "errors": [
      "Tunnel Setup: Failed to start tunnel: Request failed with status code 500",
      "Tunnel Setup: Tunnel URL is empty or invalid",
      "Diagnostics: Skipped diagnostics due to missing tunnel URL",
      "Web Test: Failed to perform web test: Command failed with code 3",
      "Web Test: Failed to perform web test: Command failed with code 3",
      "Web Test: Failed to perform web test: Command failed with code 3",
      "Web Test: Failed to perform web test: Command failed with code 3",
      "Web Test: Failed to perform web test: Command failed with code 3",
      "Web Test: Failed to perform web test: Command failed with code 3",
      "Web Test: Failed to perform web test: Command failed with code 3",
      "Web Test: Failed to perform web test: Command failed with code 3",
      "Web Test: Failed to perform web test: Command failed with code 3",
      "Web Test: Failed to perform web test: Command failed with code 3",
      "Web Test: Failed to perform web test: Command failed with code 3",
      "Web Test: Failed to perform web test: Command failed with code 3",
      "Web Test: Failed to perform web test: Command failed with code 3",
      "Web Test: Failed to perform web test: Command failed with code 3",
      "Web Test: Failed to perform web test: Command failed with code 3",
      "Tunnel Cleanup: Failed to stop tunnel: Request failed with status code 400"
    ]
  },
  {
    "toolName": "Telebit",
    "measurementNumber": 5,
    "timestamp": 3366675.60502,
    "fileTransfers": [],
    "webTests": [],
    "totalDuration": 21216.313512000255,
    "setupDuration": 11058.640457999893,
    "diagnosticsDuration": 0.014940999448299408,
    "measurementDuration": 157.1036660009995,
    "hasErrors": true,
    "errorCount": 19,
    "errors": [
      "Tunnel Setup: Failed to start tunnel: Request failed with status code 500",
      "Tunnel Setup: Tunnel URL is empty or invalid",
      "Diagnostics: Skipped diagnostics due to missing tunnel URL",
      "Web Test: Failed to perform web test: Command failed with code 3",
      "Web Test: Failed to perform web test: Command failed with code 3",
      "Web Test: Failed to perform web test: Command failed with code 3",
      "Web Test: Failed to perform web test: Command failed with code 3",
      "Web Test: Failed to perform web test: Command failed with code 3",
      "Web Test: Failed to perform web test: Command failed with code 3",
      "Web Test: Failed to perform web test: Command failed with code 3",
      "Web Test: Failed to perform web test: Command failed with code 3",
      "Web Test: Failed to perform web test: Command failed with code 3",
      "Web Test: Failed to perform web test: Command failed with code 3",
      "Web Test: Failed to perform web test: Command failed with code 3",
      "Web Test: Failed to perform web test: Command failed with code 3",
      "Web Test: Failed to perform web test: Command failed with code 3",
      "Web Test: Failed to perform web test: Command failed with code 3",
      "Web Test: Failed to perform web test: Command failed with code 3",
      "Tunnel Cleanup: Failed to stop tunnel: Request failed with status code 400"
    ]
  },
  {
    "toolName": "Telebit",
    "measurementNumber": 6,
    "timestamp": 3366688.668445,
    "fileTransfers": [],
    "webTests": [],
    "totalDuration": 21216.313512000255,
    "setupDuration": 11058.640457999893,
    "diagnosticsDuration": 0.014940999448299408,
    "measurementDuration": 157.1036660009995,
    "hasErrors": true,
    "errorCount": 19,
    "errors": [
      "Tunnel Setup: Failed to start tunnel: Request failed with status code 500",
      "Tunnel Setup: Tunnel URL is empty or invalid",
      "Diagnostics: Skipped diagnostics due to missing tunnel URL",
      "Web Test: Failed to perform web test: Command failed with code 3",
      "Web Test: Failed to perform web test: Command failed with code 3",
      "Web Test: Failed to perform web test: Command failed with code 3",
      "Web Test: Failed to perform web test: Command failed with code 3",
      "Web Test: Failed to perform web test: Command failed with code 3",
      "Web Test: Failed to perform web test: Command failed with code 3",
      "Web Test: Failed to perform web test: Command failed with code 3",
      "Web Test: Failed to perform web test: Command failed with code 3",
      "Web Test: Failed to perform web test: Command failed with code 3",
      "Web Test: Failed to perform web test: Command failed with code 3",
      "Web Test: Failed to perform web test: Command failed with code 3",
      "Web Test: Failed to perform web test: Command failed with code 3",
      "Web Test: Failed to perform web test: Command failed with code 3",
      "Web Test: Failed to perform web test: Command failed with code 3",
      "Web Test: Failed to perform web test: Command failed with code 3",
      "Tunnel Cleanup: Failed to stop tunnel: Request failed with status code 400"
    ]
  },
  {
    "toolName": "Telebit",
    "measurementNumber": 7,
    "timestamp": 3366703.029973,
    "fileTransfers": [],
    "webTests": [],
    "totalDuration": 21216.313512000255,
    "setupDuration": 11058.640457999893,
    "diagnosticsDuration": 0.014940999448299408,
    "measurementDuration": 157.1036660009995,
    "hasErrors": true,
    "errorCount": 19,
    "errors": [
      "Tunnel Setup: Failed to start tunnel: Request failed with status code 500",
      "Tunnel Setup: Tunnel URL is empty or invalid",
      "Diagnostics: Skipped diagnostics due to missing tunnel URL",
      "Web Test: Failed to perform web test: Command failed with code 3",
      "Web Test: Failed to perform web test: Command failed with code 3",
      "Web Test: Failed to perform web test: Command failed with code 3",
      "Web Test: Failed to perform web test: Command failed with code 3",
      "Web Test: Failed to perform web test: Command failed with code 3",
      "Web Test: Failed to perform web test: Command failed with code 3",
      "Web Test: Failed to perform web test: Command failed with code 3",
      "Web Test: Failed to perform web test: Command failed with code 3",
      "Web Test: Failed to perform web test: Command failed with code 3",
      "Web Test: Failed to perform web test: Command failed with code 3",
      "Web Test: Failed to perform web test: Command failed with code 3",
      "Web Test: Failed to perform web test: Command failed with code 3",
      "Web Test: Failed to perform web test: Command failed with code 3",
      "Web Test: Failed to perform web test: Command failed with code 3",
      "Web Test: Failed to perform web test: Command failed with code 3",
      "Tunnel Cleanup: Failed to stop tunnel: Request failed with status code 400"
    ]
  },
  {
    "toolName": "Telebit",
    "measurementNumber": 8,
    "timestamp": 3366714.199532,
    "fileTransfers": [],
    "webTests": [],
    "totalDuration": 21216.313512000255,
    "setupDuration": 11058.640457999893,
    "diagnosticsDuration": 0.014940999448299408,
    "measurementDuration": 157.1036660009995,
    "hasErrors": true,
    "errorCount": 19,
    "errors": [
      "Tunnel Setup: Failed to start tunnel: Request failed with status code 500",
      "Tunnel Setup: Tunnel URL is empty or invalid",
      "Diagnostics: Skipped diagnostics due to missing tunnel URL",
      "Web Test: Failed to perform web test: Command failed with code 3",
      "Web Test: Failed to perform web test: Command failed with code 3",
      "Web Test: Failed to perform web test: Command failed with code 3",
      "Web Test: Failed to perform web test: Command failed with code 3",
      "Web Test: Failed to perform web test: Command failed with code 3",
      "Web Test: Failed to perform web test: Command failed with code 3",
      "Web Test: Failed to perform web test: Command failed with code 3",
      "Web Test: Failed to perform web test: Command failed with code 3",
      "Web Test: Failed to perform web test: Command failed with code 3",
      "Web Test: Failed to perform web test: Command failed with code 3",
      "Web Test: Failed to perform web test: Command failed with code 3",
      "Web Test: Failed to perform web test: Command failed with code 3",
      "Web Test: Failed to perform web test: Command failed with code 3",
      "Web Test: Failed to perform web test: Command failed with code 3",
      "Web Test: Failed to perform web test: Command failed with code 3",
      "Tunnel Cleanup: Failed to stop tunnel: Request failed with status code 400"
    ]
  },
  {
    "toolName": "Telebit",
    "measurementNumber": 9,
    "timestamp": 3366720.6002640002,
    "fileTransfers": [],
    "webTests": [],
    "totalDuration": 21216.313512000255,
    "setupDuration": 11058.640457999893,
    "diagnosticsDuration": 0.014940999448299408,
    "measurementDuration": 157.1036660009995,
    "hasErrors": true,
    "errorCount": 19,
    "errors": [
      "Tunnel Setup: Failed to start tunnel: Request failed with status code 500",
      "Tunnel Setup: Tunnel URL is empty or invalid",
      "Diagnostics: Skipped diagnostics due to missing tunnel URL",
      "Web Test: Failed to perform web test: Command failed with code 3",
      "Web Test: Failed to perform web test: Command failed with code 3",
      "Web Test: Failed to perform web test: Command failed with code 3",
      "Web Test: Failed to perform web test: Command failed with code 3",
      "Web Test: Failed to perform web test: Command failed with code 3",
      "Web Test: Failed to perform web test: Command failed with code 3",
      "Web Test: Failed to perform web test: Command failed with code 3",
      "Web Test: Failed to perform web test: Command failed with code 3",
      "Web Test: Failed to perform web test: Command failed with code 3",
      "Web Test: Failed to perform web test: Command failed with code 3",
      "Web Test: Failed to perform web test: Command failed with code 3",
      "Web Test: Failed to perform web test: Command failed with code 3",
      "Web Test: Failed to perform web test: Command failed with code 3",
      "Web Test: Failed to perform web test: Command failed with code 3",
      "Web Test: Failed to perform web test: Command failed with code 3",
      "Tunnel Cleanup: Failed to stop tunnel: Request failed with status code 400"
    ]
  },
  {
    "toolName": "Telebit",
    "measurementNumber": 10,
    "timestamp": 3366728.471177,
    "fileTransfers": [],
    "webTests": [],
    "totalDuration": 21216.313512000255,
    "setupDuration": 11058.640457999893,
    "diagnosticsDuration": 0.014940999448299408,
    "measurementDuration": 157.1036660009995,
    "hasErrors": true,
    "errorCount": 19,
    "errors": [
      "Tunnel Setup: Failed to start tunnel: Request failed with status code 500",
      "Tunnel Setup: Tunnel URL is empty or invalid",
      "Diagnostics: Skipped diagnostics due to missing tunnel URL",
      "Web Test: Failed to perform web test: Command failed with code 3",
      "Web Test: Failed to perform web test: Command failed with code 3",
      "Web Test: Failed to perform web test: Command failed with code 3",
      "Web Test: Failed to perform web test: Command failed with code 3",
      "Web Test: Failed to perform web test: Command failed with code 3",
      "Web Test: Failed to perform web test: Command failed with code 3",
      "Web Test: Failed to perform web test: Command failed with code 3",
      "Web Test: Failed to perform web test: Command failed with code 3",
      "Web Test: Failed to perform web test: Command failed with code 3",
      "Web Test: Failed to perform web test: Command failed with code 3",
      "Web Test: Failed to perform web test: Command failed with code 3",
      "Web Test: Failed to perform web test: Command failed with code 3",
      "Web Test: Failed to perform web test: Command failed with code 3",
      "Web Test: Failed to perform web test: Command failed with code 3",
      "Web Test: Failed to perform web test: Command failed with code 3",
      "Tunnel Cleanup: Failed to stop tunnel: Request failed with status code 400"
    ]
  },
  {
    "toolName": "Telebit",
    "measurementNumber": 11,
    "timestamp": 3366734.7016100003,
    "fileTransfers": [],
    "webTests": [],
    "totalDuration": 21216.313512000255,
    "setupDuration": 11058.640457999893,
    "diagnosticsDuration": 0.014940999448299408,
    "measurementDuration": 157.1036660009995,
    "hasErrors": true,
    "errorCount": 19,
    "errors": [
      "Tunnel Setup: Failed to start tunnel: Request failed with status code 500",
      "Tunnel Setup: Tunnel URL is empty or invalid",
      "Diagnostics: Skipped diagnostics due to missing tunnel URL",
      "Web Test: Failed to perform web test: Command failed with code 3",
      "Web Test: Failed to perform web test: Command failed with code 3",
      "Web Test: Failed to perform web test: Command failed with code 3",
      "Web Test: Failed to perform web test: Command failed with code 3",
      "Web Test: Failed to perform web test: Command failed with code 3",
      "Web Test: Failed to perform web test: Command failed with code 3",
      "Web Test: Failed to perform web test: Command failed with code 3",
      "Web Test: Failed to perform web test: Command failed with code 3",
      "Web Test: Failed to perform web test: Command failed with code 3",
      "Web Test: Failed to perform web test: Command failed with code 3",
      "Web Test: Failed to perform web test: Command failed with code 3",
      "Web Test: Failed to perform web test: Command failed with code 3",
      "Web Test: Failed to perform web test: Command failed with code 3",
      "Web Test: Failed to perform web test: Command failed with code 3",
      "Web Test: Failed to perform web test: Command failed with code 3",
      "Tunnel Cleanup: Failed to stop tunnel: Request failed with status code 400"
    ]
  },
  {
    "toolName": "Telebit",
    "measurementNumber": 12,
    "timestamp": 3366740.835083,
    "fileTransfers": [],
    "webTests": [],
    "totalDuration": 21216.313512000255,
    "setupDuration": 11058.640457999893,
    "diagnosticsDuration": 0.014940999448299408,
    "measurementDuration": 157.1036660009995,
    "hasErrors": true,
    "errorCount": 19,
    "errors": [
      "Tunnel Setup: Failed to start tunnel: Request failed with status code 500",
      "Tunnel Setup: Tunnel URL is empty or invalid",
      "Diagnostics: Skipped diagnostics due to missing tunnel URL",
      "Web Test: Failed to perform web test: Command failed with code 3",
      "Web Test: Failed to perform web test: Command failed with code 3",
      "Web Test: Failed to perform web test: Command failed with code 3",
      "Web Test: Failed to perform web test: Command failed with code 3",
      "Web Test: Failed to perform web test: Command failed with code 3",
      "Web Test: Failed to perform web test: Command failed with code 3",
      "Web Test: Failed to perform web test: Command failed with code 3",
      "Web Test: Failed to perform web test: Command failed with code 3",
      "Web Test: Failed to perform web test: Command failed with code 3",
      "Web Test: Failed to perform web test: Command failed with code 3",
      "Web Test: Failed to perform web test: Command failed with code 3",
      "Web Test: Failed to perform web test: Command failed with code 3",
      "Web Test: Failed to perform web test: Command failed with code 3",
      "Web Test: Failed to perform web test: Command failed with code 3",
      "Web Test: Failed to perform web test: Command failed with code 3",
      "Tunnel Cleanup: Failed to stop tunnel: Request failed with status code 400"
    ]
  },
  {
    "toolName": "Telebit",
    "measurementNumber": 13,
    "timestamp": 3366746.39973,
    "fileTransfers": [],
    "webTests": [],
    "totalDuration": 21216.313512000255,
    "setupDuration": 11058.640457999893,
    "diagnosticsDuration": 0.014940999448299408,
    "measurementDuration": 157.1036660009995,
    "hasErrors": true,
    "errorCount": 19,
    "errors": [
      "Tunnel Setup: Failed to start tunnel: Request failed with status code 500",
      "Tunnel Setup: Tunnel URL is empty or invalid",
      "Diagnostics: Skipped diagnostics due to missing tunnel URL",
      "Web Test: Failed to perform web test: Command failed with code 3",
      "Web Test: Failed to perform web test: Command failed with code 3",
      "Web Test: Failed to perform web test: Command failed with code 3",
      "Web Test: Failed to perform web test: Command failed with code 3",
      "Web Test: Failed to perform web test: Command failed with code 3",
      "Web Test: Failed to perform web test: Command failed with code 3",
      "Web Test: Failed to perform web test: Command failed with code 3",
      "Web Test: Failed to perform web test: Command failed with code 3",
      "Web Test: Failed to perform web test: Command failed with code 3",
      "Web Test: Failed to perform web test: Command failed with code 3",
      "Web Test: Failed to perform web test: Command failed with code 3",
      "Web Test: Failed to perform web test: Command failed with code 3",
      "Web Test: Failed to perform web test: Command failed with code 3",
      "Web Test: Failed to perform web test: Command failed with code 3",
      "Web Test: Failed to perform web test: Command failed with code 3",
      "Tunnel Cleanup: Failed to stop tunnel: Request failed with status code 400"
    ]
  },
  {
    "toolName": "Telebit",
    "measurementNumber": 14,
    "timestamp": 3366754.4386470006,
    "fileTransfers": [],
    "webTests": [],
    "totalDuration": 21216.313512000255,
    "setupDuration": 11058.640457999893,
    "diagnosticsDuration": 0.014940999448299408,
    "measurementDuration": 157.1036660009995,
    "hasErrors": true,
    "errorCount": 19,
    "errors": [
      "Tunnel Setup: Failed to start tunnel: Request failed with status code 500",
      "Tunnel Setup: Tunnel URL is empty or invalid",
      "Diagnostics: Skipped diagnostics due to missing tunnel URL",
      "Web Test: Failed to perform web test: Command failed with code 3",
      "Web Test: Failed to perform web test: Command failed with code 3",
      "Web Test: Failed to perform web test: Command failed with code 3",
      "Web Test: Failed to perform web test: Command failed with code 3",
      "Web Test: Failed to perform web test: Command failed with code 3",
      "Web Test: Failed to perform web test: Command failed with code 3",
      "Web Test: Failed to perform web test: Command failed with code 3",
      "Web Test: Failed to perform web test: Command failed with code 3",
      "Web Test: Failed to perform web test: Command failed with code 3",
      "Web Test: Failed to perform web test: Command failed with code 3",
      "Web Test: Failed to perform web test: Command failed with code 3",
      "Web Test: Failed to perform web test: Command failed with code 3",
      "Web Test: Failed to perform web test: Command failed with code 3",
      "Web Test: Failed to perform web test: Command failed with code 3",
      "Web Test: Failed to perform web test: Command failed with code 3",
      "Tunnel Cleanup: Failed to stop tunnel: Request failed with status code 400"
    ]
  },
  {
    "toolName": "Telebit",
    "measurementNumber": 15,
    "timestamp": 3366764.193804,
    "fileTransfers": [],
    "webTests": [],
    "totalDuration": 21216.313512000255,
    "setupDuration": 11058.640457999893,
    "diagnosticsDuration": 0.014940999448299408,
    "measurementDuration": 157.1036660009995,
    "hasErrors": true,
    "errorCount": 19,
    "errors": [
      "Tunnel Setup: Failed to start tunnel: Request failed with status code 500",
      "Tunnel Setup: Tunnel URL is empty or invalid",
      "Diagnostics: Skipped diagnostics due to missing tunnel URL",
      "Web Test: Failed to perform web test: Command failed with code 3",
      "Web Test: Failed to perform web test: Command failed with code 3",
      "Web Test: Failed to perform web test: Command failed with code 3",
      "Web Test: Failed to perform web test: Command failed with code 3",
      "Web Test: Failed to perform web test: Command failed with code 3",
      "Web Test: Failed to perform web test: Command failed with code 3",
      "Web Test: Failed to perform web test: Command failed with code 3",
      "Web Test: Failed to perform web test: Command failed with code 3",
      "Web Test: Failed to perform web test: Command failed with code 3",
      "Web Test: Failed to perform web test: Command failed with code 3",
      "Web Test: Failed to perform web test: Command failed with code 3",
      "Web Test: Failed to perform web test: Command failed with code 3",
      "Web Test: Failed to perform web test: Command failed with code 3",
      "Web Test: Failed to perform web test: Command failed with code 3",
      "Web Test: Failed to perform web test: Command failed with code 3",
      "Tunnel Cleanup: Failed to stop tunnel: Request failed with status code 400"
    ]
  }
]