[
  {
    "toolName": "Ngtor",
    "measurementNumber": 1,
    "timestamp": 3899383.594795,
    "fileTransfers": [
      {
        "filename": "10MB.txt",
        "timestamp": 3899383.600149,
        "fileSize": 10485760,
        "contentType": "text/plain",
        "transferSuccess": true,
        "statusCode": 200,
        "downloadSpeed": 500627,
        "uploadSpeed": 0,
        "dnsLookup": 0.02,
        "tcpConnection": 0.09000000000000001,
        "tlsHandshake": 0,
        "timeToFirstByte": 4013.3279999999995,
        "totalTransferTime": 20945.25,
        "hashMatch": true,
        "sizeMatch": true
      },
      {
        "filename": "1MB.txt",
        "timestamp": 3920368.4066279996,
        "fileSize": 1048576,
        "contentType": "text/plain",
        "transferSuccess": true,
        "statusCode": 200,
        "downloadSpeed": 418760,
        "uploadSpeed": 0,
        "dnsLookup": 0.024,
        "tcpConnection": 0.114,
        "tlsHandshake": 0,
        "timeToFirstByte": 1178.0729999999999,
        "totalTransferTime": 2504.002,
        "hashMatch": true,
        "sizeMatch": true
      },
      {
        "filename": "25MB.txt",
        "timestamp": 3922884.3661899995,
        "fileSize": 26214400,
        "contentType": "text/plain",
        "transferSuccess": true,
        "statusCode": 200,
        "downloadSpeed": 700885,
        "uploadSpeed": 0,
        "dnsLookup": 0.02,
        "tcpConnection": 0.09000000000000001,
        "tlsHandshake": 0,
        "timeToFirstByte": 1206.532,
        "totalTransferTime": 37401.827,
        "hashMatch": true,
        "sizeMatch": true
      }
    ],
    "webTests": [
      {
        "url": "http://djtlsvpcjznwr2lx22cggeetjvzk75k6uzm5nhaoozbr3zqlfpb2fdid.onion/webtest",
        "statusCode": 200,
        "downloadSpeed": 2327,
        "uploadSpeed": 0,
        "dnsLookup": 0.02,
        "tcpConnection": 0.08399999999999999,
        "tlsHandshake": 0,
        "timeToFirstByte": 1043.334,
        "totalTime": 1043.445,
        "fcp": 0,
        "lcp": 0,
        "error": "Playwright error: page.goto: net::ERR_NAME_NOT_RESOLVED at http://djtlsvpcjznwr2lx22cggeetjvzk75k6uzm5nhaoozbr3zqlfpb2fdid.onion/webtest\nCall log:\n\u001b[2m  - navigating to \"http://djtlsvpcjznwr2lx22cggeetjvzk75k6uzm5nhaoozbr3zqlfpb2fdid.onion/webtest\", waiting until \"load\"\u001b[22m\n"
      }
    ],
    "totalDuration": 976210.0449420027,
    "setupDuration": 8529.162531999871,
    "diagnosticsDuration": 0.005168000236153603,
    "measurementDuration": 957676.618340997,
    "hasErrors": false,
    "errorCount": 0,
    "errors": []
  },
  {
    "toolName": "Ngtor",
    "measurementNumber": 2,
    "timestamp": 3961634.5392499994,
    "fileTransfers": [
      {
        "filename": "10MB.txt",
        "timestamp": 3961634.543091001,
        "fileSize": 10485760,
        "contentType": "text/plain",
        "transferSuccess": true,
        "statusCode": 200,
        "downloadSpeed": 552772,
        "uploadSpeed": 0,
        "dnsLookup": 0.020999999999999998,
        "tcpConnection": 0.092,
        "tlsHandshake": 0,
        "timeToFirstByte": 925.526,
        "totalTransferTime": 18969.401,
        "hashMatch": true,
        "sizeMatch": true
      },
      {
        "filename": "1MB.txt",
        "timestamp": 3980647.3891589995,
        "fileSize": 1048576,
        "contentType": "text/plain",
        "transferSuccess": true,
        "statusCode": 200,
        "downloadSpeed": 366791,
        "uploadSpeed": 0,
        "dnsLookup": 0.019,
        "tcpConnection": 0.088,
        "tlsHandshake": 0,
        "timeToFirstByte": 1277.586,
        "totalTransferTime": 2858.7799999999997,
        "hashMatch": true,
        "sizeMatch": true
      },
      {
        "filename": "25MB.txt",
        "timestamp": 3983520.077903999,
        "fileSize": 26214400,
        "contentType": "text/plain",
        "transferSuccess": true,
        "statusCode": 200,
        "downloadSpeed": 695433,
        "uploadSpeed": 0,
        "dnsLookup": 0.022,
        "tcpConnection": 0.092,
        "tlsHandshake": 0,
        "timeToFirstByte": 1146.154,
        "totalTransferTime": 37695.072,
        "hashMatch": true,
        "sizeMatch": true
      }
    ],
    "webTests": [
      {
        "url": "http://djtlsvpcjznwr2lx22cggeetjvzk75k6uzm5nhaoozbr3zqlfpb2fdid.onion/webtest",
        "statusCode": 200,
        "downloadSpeed": 2363,
        "uploadSpeed": 0,
        "dnsLookup": 0.019,
        "tcpConnection": 0.082,
        "tlsHandshake": 0,
        "timeToFirstByte": 1027.437,
        "totalTime": 1027.5529999999999,
        "fcp": 0,
        "lcp": 0,
        "error": "Playwright error: page.goto: net::ERR_NAME_NOT_RESOLVED at http://djtlsvpcjznwr2lx22cggeetjvzk75k6uzm5nhaoozbr3zqlfpb2fdid.onion/webtest\nCall log:\n\u001b[2m  - navigating to \"http://djtlsvpcjznwr2lx22cggeetjvzk75k6uzm5nhaoozbr3zqlfpb2fdid.onion/webtest\", waiting until \"load\"\u001b[22m\n"
      }
    ],
    "totalDuration": 976210.0449420027,
    "setupDuration": 8529.162531999871,
    "diagnosticsDuration": 0.005168000236153603,
    "measurementDuration": 957676.618340997,
    "hasErrors": false,
    "errorCount": 0,
    "errors": []
  },
  {
    "toolName": "Ngtor",
    "measurementNumber": 3,
    "timestamp": 4022508.627680002,
    "fileTransfers": [
      {
        "filename": "10MB.txt",
        "timestamp": 4022508.62961,
        "fileSize": 10485760,
        "contentType": "text/plain",
        "transferSuccess": true,
        "statusCode": 200,
        "downloadSpeed": 551171,
        "uploadSpeed": 0,
        "dnsLookup": 0.018000000000000002,
        "tcpConnection": 0.073,
        "tlsHandshake": 0,
        "timeToFirstByte": 1110.586,
        "totalTransferTime": 19024.513,
        "hashMatch": true,
        "sizeMatch": true
      },
      {
        "filename": "1MB.txt",
        "timestamp": 4041573.5757379998,
        "fileSize": 1048576,
        "contentType": "text/plain",
        "transferSuccess": true,
        "statusCode": 200,
        "downloadSpeed": 404158,
        "uploadSpeed": 0,
        "dnsLookup": 0.019,
        "tcpConnection": 0.09000000000000001,
        "tlsHandshake": 0,
        "timeToFirstByte": 1127.785,
        "totalTransferTime": 2594.469,
        "hashMatch": true,
        "sizeMatch": true
      },
      {
        "filename": "25MB.txt",
        "timestamp": 4044181.558358999,
        "fileSize": 26214400,
        "contentType": "text/plain",
        "transferSuccess": true,
        "statusCode": 200,
        "downloadSpeed": 752684,
        "uploadSpeed": 0,
        "dnsLookup": 0.028,
        "tcpConnection": 0.122,
        "tlsHandshake": 0,
        "timeToFirstByte": 1129.88,
        "totalTransferTime": 34827.895,
        "hashMatch": true,
        "sizeMatch": true
      }
    ],
    "webTests": [
      {
        "url": "http://djtlsvpcjznwr2lx22cggeetjvzk75k6uzm5nhaoozbr3zqlfpb2fdid.onion/webtest",
        "statusCode": 200,
        "downloadSpeed": 2257,
        "uploadSpeed": 0,
        "dnsLookup": 0.019,
        "tcpConnection": 0.08,
        "tlsHandshake": 0,
        "timeToFirstByte": 1076.0620000000001,
        "totalTime": 1076.203,
        "fcp": 0,
        "lcp": 0,
        "error": "Playwright error: page.goto: net::ERR_NAME_NOT_RESOLVED at http://djtlsvpcjznwr2lx22cggeetjvzk75k6uzm5nhaoozbr3zqlfpb2fdid.onion/webtest\nCall log:\n\u001b[2m  - navigating to \"http://djtlsvpcjznwr2lx22cggeetjvzk75k6uzm5nhaoozbr3zqlfpb2fdid.onion/webtest\", waiting until \"load\"\u001b[22m\n"
      }
    ],
    "totalDuration": 976210.0449420027,
    "setupDuration": 8529.162531999871,
    "diagnosticsDuration": 0.005168000236153603,
    "measurementDuration": 957676.618340997,
    "hasErrors": false,
    "errorCount": 0,
    "errors": []
  },
  {
    "toolName": "Ngtor",
    "measurementNumber": 4,
    "timestamp": 4080371.314461002,
    "fileTransfers": [
      {
        "filename": "10MB.txt",
        "timestamp": 4080371.3193730023,
        "fileSize": 10485760,
        "contentType": "text/plain",
        "transferSuccess": true,
        "statusCode": 200,
        "downloadSpeed": 538836,
        "uploadSpeed": 0,
        "dnsLookup": 0.019,
        "tcpConnection": 0.075,
        "tlsHandshake": 0,
        "timeToFirstByte": 1006.0100000000001,
        "totalTransferTime": 19459.994,
        "hashMatch": true,
        "sizeMatch": true
      },
      {
        "filename": "1MB.txt",
        "timestamp": 4099872.4848490003,
        "fileSize": 1048576,
        "contentType": "text/plain",
        "transferSuccess": true,
        "statusCode": 200,
        "downloadSpeed": 344607,
        "uploadSpeed": 0,
        "dnsLookup": 0.019,
        "tcpConnection": 0.08600000000000001,
        "tlsHandshake": 0,
        "timeToFirstByte": 1157.009,
        "totalTransferTime": 3042.81,
        "hashMatch": true,
        "sizeMatch": true
      },
      {
        "filename": "25MB.txt",
        "timestamp": 4102930.292901,
        "fileSize": 26214400,
        "contentType": "text/plain",
        "transferSuccess": true,
        "statusCode": 200,
        "downloadSpeed": 651296,
        "uploadSpeed": 0,
        "dnsLookup": 0.028,
        "tcpConnection": 0.112,
        "tlsHandshake": 0,
        "timeToFirstByte": 1087.193,
        "totalTransferTime": 40249.539,
        "hashMatch": true,
        "sizeMatch": true
      }
    ],
    "webTests": [
      {
        "url": "http://djtlsvpcjznwr2lx22cggeetjvzk75k6uzm5nhaoozbr3zqlfpb2fdid.onion/webtest",
        "statusCode": 200,
        "downloadSpeed": 1884,
        "uploadSpeed": 0,
        "dnsLookup": 0.036000000000000004,
        "tcpConnection": 0.136,
        "tlsHandshake": 0,
        "timeToFirstByte": 1288.535,
        "totalTime": 1288.756,
        "fcp": 0,
        "lcp": 0,
        "error": "Playwright error: page.goto: net::ERR_NAME_NOT_RESOLVED at http://djtlsvpcjznwr2lx22cggeetjvzk75k6uzm5nhaoozbr3zqlfpb2fdid.onion/webtest\nCall log:\n\u001b[2m  - navigating to \"http://djtlsvpcjznwr2lx22cggeetjvzk75k6uzm5nhaoozbr3zqlfpb2fdid.onion/webtest\", waiting until \"load\"\u001b[22m\n"
      }
    ],
    "totalDuration": 976210.0449420027,
    "setupDuration": 8529.162531999871,
    "diagnosticsDuration": 0.005168000236153603,
    "measurementDuration": 957676.618340997,
    "hasErrors": false,
    "errorCount": 0,
    "errors": []
  },
  {
    "toolName": "Ngtor",
    "measurementNumber": 5,
    "timestamp": 4144758.7702120002,
    "fileTransfers": [
      {
        "filename": "10MB.txt",
        "timestamp": 4144758.772306001,
        "fileSize": 10485760,
        "contentType": "text/plain",
        "transferSuccess": true,
        "statusCode": 200,
        "downloadSpeed": 535367,
        "uploadSpeed": 0,
        "dnsLookup": 0.019,
        "tcpConnection": 0.074,
        "tlsHandshake": 0,
        "timeToFirstByte": 1002.473,
        "totalTransferTime": 19586.114999999998,
        "hashMatch": true,
        "sizeMatch": true
      },
      {
        "filename": "1MB.txt",
        "timestamp": 4164375.7826230023,
        "fileSize": 1048576,
        "contentType": "text/plain",
        "transferSuccess": true,
        "statusCode": 200,
        "downloadSpeed": 327546,
        "uploadSpeed": 0,
        "dnsLookup": 0.022,
        "tcpConnection": 0.088,
        "tlsHandshake": 0,
        "timeToFirstByte": 1147.019,
        "totalTransferTime": 3201.307,
        "hashMatch": true,
        "sizeMatch": true
      },
      {
        "filename": "25MB.txt",
        "timestamp": 4167587.1149190012,
        "fileSize": 26214400,
        "contentType": "text/plain",
        "transferSuccess": true,
        "statusCode": 200,
        "downloadSpeed": 650086,
        "uploadSpeed": 0,
        "dnsLookup": 0.033,
        "tcpConnection": 0.122,
        "tlsHandshake": 0,
        "timeToFirstByte": 1320.91,
        "totalTransferTime": 40324.458999999995,
        "hashMatch": true,
        "sizeMatch": true
      }
    ],
    "webTests": [
      {
        "url": "http://djtlsvpcjznwr2lx22cggeetjvzk75k6uzm5nhaoozbr3zqlfpb2fdid.onion/webtest",
        "statusCode": 200,
        "downloadSpeed": 1934,
        "uploadSpeed": 0,
        "dnsLookup": 0.02,
        "tcpConnection": 0.08,
        "tlsHandshake": 0,
        "timeToFirstByte": 1255.474,
        "totalTime": 1255.604,
        "fcp": 0,
        "lcp": 0,
        "error": "Playwright error: page.goto: net::ERR_NAME_NOT_RESOLVED at http://djtlsvpcjznwr2lx22cggeetjvzk75k6uzm5nhaoozbr3zqlfpb2fdid.onion/webtest\nCall log:\n\u001b[2m  - navigating to \"http://djtlsvpcjznwr2lx22cggeetjvzk75k6uzm5nhaoozbr3zqlfpb2fdid.onion/webtest\", waiting until \"load\"\u001b[22m\n"
      }
    ],
    "totalDuration": 976210.0449420027,
    "setupDuration": 8529.162531999871,
    "diagnosticsDuration": 0.005168000236153603,
    "measurementDuration": 957676.618340997,
    "hasErrors": false,
    "errorCount": 0,
    "errors": []
  },
  {
    "toolName": "Ngtor",
    "measurementNumber": 6,
    "timestamp": 4209446.404901,
    "fileTransfers": [
      {
        "filename": "10MB.txt",
        "timestamp": 4209446.411815999,
        "fileSize": 10485760,
        "contentType": "text/plain",
        "transferSuccess": true,
        "statusCode": 200,
        "downloadSpeed": 531157,
        "uploadSpeed": 0,
        "dnsLookup": 0.018000000000000002,
        "tcpConnection": 0.08,
        "tlsHandshake": 0,
        "timeToFirstByte": 1021.6339999999999,
        "totalTransferTime": 19741.356,
        "hashMatch": true,
        "sizeMatch": true
      },
      {
        "filename": "1MB.txt",
        "timestamp": 4229217.789802002,
        "fileSize": 1048576,
        "contentType": "text/plain",
        "transferSuccess": true,
        "statusCode": 200,
        "downloadSpeed": 353706,
        "uploadSpeed": 0,
        "dnsLookup": 0.031,
        "tcpConnection": 0.10900000000000001,
        "tlsHandshake": 0,
        "timeToFirstByte": 1237.913,
        "totalTransferTime": 2964.538,
        "hashMatch": true,
        "sizeMatch": true
      },
      {
        "filename": "25MB.txt",
        "timestamp": 4232198.2217930015,
        "fileSize": 26214400,
        "contentType": "text/plain",
        "transferSuccess": true,
        "statusCode": 200,
        "downloadSpeed": 666978,
        "uploadSpeed": 0,
        "dnsLookup": 0.020999999999999998,
        "tcpConnection": 0.088,
        "tlsHandshake": 0,
        "timeToFirstByte": 1435.21,
        "totalTransferTime": 39303.195,
        "hashMatch": true,
        "sizeMatch": true
      }
    ],
    "webTests": [
      {
        "url": "http://djtlsvpcjznwr2lx22cggeetjvzk75k6uzm5nhaoozbr3zqlfpb2fdid.onion/webtest",
        "statusCode": 200,
        "downloadSpeed": 2233,
        "uploadSpeed": 0,
        "dnsLookup": 0.02,
        "tcpConnection": 0.08600000000000001,
        "tlsHandshake": 0,
        "timeToFirstByte": 1087.1779999999999,
        "totalTime": 1087.289,
        "fcp": 0,
        "lcp": 0,
        "error": "Playwright error: page.goto: net::ERR_NAME_NOT_RESOLVED at http://djtlsvpcjznwr2lx22cggeetjvzk75k6uzm5nhaoozbr3zqlfpb2fdid.onion/webtest\nCall log:\n\u001b[2m  - navigating to \"http://djtlsvpcjznwr2lx22cggeetjvzk75k6uzm5nhaoozbr3zqlfpb2fdid.onion/webtest\", waiting until \"load\"\u001b[22m\n"
      }
    ],
    "totalDuration": 976210.0449420027,
    "setupDuration": 8529.162531999871,
    "diagnosticsDuration": 0.005168000236153603,
    "measurementDuration": 957676.618340997,
    "hasErrors": false,
    "errorCount": 0,
    "errors": []
  },
  {
    "toolName": "Ngtor",
    "measurementNumber": 7,
    "timestamp": 4272883.675217999,
    "fileTransfers": [
      {
        "filename": "10MB.txt",
        "timestamp": 4272883.684269002,
        "fileSize": 10485760,
        "contentType": "text/plain",
        "transferSuccess": true,
        "statusCode": 200,
        "downloadSpeed": 486986,
        "uploadSpeed": 0,
        "dnsLookup": 0.022,
        "tcpConnection": 0.089,
        "tlsHandshake": 0,
        "timeToFirstByte": 1064.8249999999998,
        "totalTransferTime": 21531.915999999997,
        "hashMatch": true,
        "sizeMatch": true
      },
      {
        "filename": "1MB.txt",
        "timestamp": 4294453.572559999,
        "fileSize": 1048576,
        "contentType": "text/plain",
        "transferSuccess": true,
        "statusCode": 200,
        "downloadSpeed": 431012,
        "uploadSpeed": 0,
        "dnsLookup": 0.019,
        "tcpConnection": 0.078,
        "tlsHandshake": 0,
        "timeToFirstByte": 948.467,
        "totalTransferTime": 2432.821,
        "hashMatch": true,
        "sizeMatch": true
      },
      {
        "filename": "25MB.txt",
        "timestamp": 4296899.795316001,
        "fileSize": 26214400,
        "contentType": "text/plain",
        "transferSuccess": true,
        "statusCode": 200,
        "downloadSpeed": 624294,
        "uploadSpeed": 0,
        "dnsLookup": 0.045000000000000005,
        "tcpConnection": 0.18100000000000002,
        "tlsHandshake": 0,
        "timeToFirstByte": 1224.944,
        "totalTransferTime": 41990.432,
        "hashMatch": true,
        "sizeMatch": true
      }
    ],
    "webTests": [
      {
        "url": "http://djtlsvpcjznwr2lx22cggeetjvzk75k6uzm5nhaoozbr3zqlfpb2fdid.onion/webtest",
        "statusCode": 200,
        "downloadSpeed": 2176,
        "uploadSpeed": 0,
        "dnsLookup": 0.018000000000000002,
        "tcpConnection": 0.082,
        "tlsHandshake": 0,
        "timeToFirstByte": 1116.0079999999998,
        "totalTime": 1116.153,
        "fcp": 0,
        "lcp": 0,
        "error": "Playwright error: page.goto: net::ERR_NAME_NOT_RESOLVED at http://djtlsvpcjznwr2lx22cggeetjvzk75k6uzm5nhaoozbr3zqlfpb2fdid.onion/webtest\nCall log:\n\u001b[2m  - navigating to \"http://djtlsvpcjznwr2lx22cggeetjvzk75k6uzm5nhaoozbr3zqlfpb2fdid.onion/webtest\", waiting until \"load\"\u001b[22m\n"
      }
    ],
    "totalDuration": 976210.0449420027,
    "setupDuration": 8529.162531999871,
    "diagnosticsDuration": 0.005168000236153603,
    "measurementDuration": 957676.618340997,
    "hasErrors": false,
    "errorCount": 0,
    "errors": []
  },
  {
    "toolName": "Ngtor",
    "measurementNumber": 8,
    "timestamp": 4340353.7856020015,
    "fileTransfers": [
      {
        "filename": "10MB.txt",
        "timestamp": 4340353.789929999,
        "fileSize": 10485760,
        "contentType": "text/plain",
        "transferSuccess": true,
        "statusCode": 200,
        "downloadSpeed": 574366,
        "uploadSpeed": 0,
        "dnsLookup": 0.034,
        "tcpConnection": 0.16699999999999998,
        "tlsHandshake": 0,
        "timeToFirstByte": 946.827,
        "totalTransferTime": 18256.215,
        "hashMatch": true,
        "sizeMatch": true
      },
      {
        "filename": "1MB.txt",
        "timestamp": 4358654.823519999,
        "fileSize": 1048576,
        "contentType": "text/plain",
        "transferSuccess": true,
        "statusCode": 200,
        "downloadSpeed": 388743,
        "uploadSpeed": 0,
        "dnsLookup": 0.019,
        "tcpConnection": 0.082,
        "tlsHandshake": 0,
        "timeToFirstByte": 1218.51,
        "totalTransferTime": 2697.349,
        "hashMatch": true,
        "sizeMatch": true
      },
      {
        "filename": "25MB.txt",
        "timestamp": 4361365.692658002,
        "fileSize": 26214400,
        "contentType": "text/plain",
        "transferSuccess": true,
        "statusCode": 200,
        "downloadSpeed": 606398,
        "uploadSpeed": 0,
        "dnsLookup": 0.025,
        "tcpConnection": 0.10900000000000001,
        "tlsHandshake": 0,
        "timeToFirstByte": 1403.87,
        "totalTransferTime": 43229.643000000004,
        "hashMatch": true,
        "sizeMatch": true
      }
    ],
    "webTests": [
      {
        "url": "http://djtlsvpcjznwr2lx22cggeetjvzk75k6uzm5nhaoozbr3zqlfpb2fdid.onion/webtest",
        "statusCode": 200,
        "downloadSpeed": 2328,
        "uploadSpeed": 0,
        "dnsLookup": 0.02,
        "tcpConnection": 0.097,
        "tlsHandshake": 0,
        "timeToFirstByte": 1042.737,
        "totalTime": 1042.96,
        "fcp": 0,
        "lcp": 0,
        "error": "Playwright error: page.goto: net::ERR_NAME_NOT_RESOLVED at http://djtlsvpcjznwr2lx22cggeetjvzk75k6uzm5nhaoozbr3zqlfpb2fdid.onion/webtest\nCall log:\n\u001b[2m  - navigating to \"http://djtlsvpcjznwr2lx22cggeetjvzk75k6uzm5nhaoozbr3zqlfpb2fdid.onion/webtest\", waiting until \"load\"\u001b[22m\n"
      }
    ],
    "totalDuration": 976210.0449420027,
    "setupDuration": 8529.162531999871,
    "diagnosticsDuration": 0.005168000236153603,
    "measurementDuration": 957676.618340997,
    "hasErrors": false,
    "errorCount": 0,
    "errors": []
  },
  {
    "toolName": "Ngtor",
    "measurementNumber": 9,
    "timestamp": 4405936.167398,
    "fileTransfers": [
      {
        "filename": "10MB.txt",
        "timestamp": 4405936.170406999,
        "fileSize": 10485760,
        "contentType": "text/plain",
        "transferSuccess": true,
        "statusCode": 200,
        "downloadSpeed": 469150,
        "uploadSpeed": 0,
        "dnsLookup": 0.025,
        "tcpConnection": 0.09899999999999999,
        "tlsHandshake": 0,
        "timeToFirstByte": 1322.093,
        "totalTransferTime": 22350.517,
        "hashMatch": true,
        "sizeMatch": true
      },
      {
        "filename": "1MB.txt",
        "timestamp": 4428321.1854610015,
        "fileSize": 1048576,
        "contentType": "text/plain",
        "transferSuccess": true,
        "statusCode": 200,
        "downloadSpeed": 229620,
        "uploadSpeed": 0,
        "dnsLookup": 0.02,
        "tcpConnection": 0.088,
        "tlsHandshake": 0,
        "timeToFirstByte": 1930.013,
        "totalTransferTime": 4566.567,
        "hashMatch": true,
        "sizeMatch": true
      },
      {
        "filename": "25MB.txt",
        "timestamp": 4432900.744950002,
        "fileSize": 26214400,
        "contentType": "text/plain",
        "transferSuccess": true,
        "statusCode": 200,
        "downloadSpeed": 622216,
        "uploadSpeed": 0,
        "dnsLookup": 0.026,
        "tcpConnection": 0.107,
        "tlsHandshake": 0,
        "timeToFirstByte": 1282.203,
        "totalTransferTime": 42130.671,
        "hashMatch": true,
        "sizeMatch": true
      }
    ],
    "webTests": [
      {
        "url": "http://djtlsvpcjznwr2lx22cggeetjvzk75k6uzm5nhaoozbr3zqlfpb2fdid.onion/webtest",
        "statusCode": 200,
        "downloadSpeed": 1407,
        "uploadSpeed": 0,
        "dnsLookup": 0.019,
        "tcpConnection": 0.089,
        "tlsHandshake": 0,
        "timeToFirstByte": 1726.23,
        "totalTime": 1726.3500000000001,
        "fcp": 0,
        "lcp": 0,
        "error": "Playwright error: page.goto: net::ERR_NAME_NOT_RESOLVED at http://djtlsvpcjznwr2lx22cggeetjvzk75k6uzm5nhaoozbr3zqlfpb2fdid.onion/webtest\nCall log:\n\u001b[2m  - navigating to \"http://djtlsvpcjznwr2lx22cggeetjvzk75k6uzm5nhaoozbr3zqlfpb2fdid.onion/webtest\", waiting until \"load\"\u001b[22m\n"
      }
    ],
    "totalDuration": 976210.0449420027,
    "setupDuration": 8529.162531999871,
    "diagnosticsDuration": 0.005168000236153603,
    "measurementDuration": 957676.618340997,
    "hasErrors": false,
    "errorCount": 0,
    "errors": []
  },
  {
    "toolName": "Ngtor",
    "measurementNumber": 10,
    "timestamp": 4477061.854482999,
    "fileTransfers": [
      {
        "filename": "10MB.txt",
        "timestamp": 4477061.856588999,
        "fileSize": 10485760,
        "contentType": "text/plain",
        "transferSuccess": true,
        "statusCode": 200,
        "downloadSpeed": 542774,
        "uploadSpeed": 0,
        "dnsLookup": 0.059,
        "tcpConnection": 0.11699999999999999,
        "tlsHandshake": 0,
        "timeToFirstByte": 1176.824,
        "totalTransferTime": 19318.831,
        "hashMatch": true,
        "sizeMatch": true
      },
      {
        "filename": "1MB.txt",
        "timestamp": 4496415.214415001,
        "fileSize": 1048576,
        "contentType": "text/plain",
        "transferSuccess": true,
        "statusCode": 200,
        "downloadSpeed": 283899,
        "uploadSpeed": 0,
        "dnsLookup": 0.019,
        "tcpConnection": 0.075,
        "tlsHandshake": 0,
        "timeToFirstByte": 1245.794,
        "totalTransferTime": 3693.476,
        "hashMatch": true,
        "sizeMatch": true
      },
      {
        "filename": "25MB.txt",
        "timestamp": 4500121.459028,
        "fileSize": 26214400,
        "contentType": "text/plain",
        "transferSuccess": true,
        "statusCode": 200,
        "downloadSpeed": 584576,
        "uploadSpeed": 0,
        "dnsLookup": 0.019,
        "tcpConnection": 0.083,
        "tlsHandshake": 0,
        "timeToFirstByte": 1222.9080000000001,
        "totalTransferTime": 44843.422,
        "hashMatch": true,
        "sizeMatch": true
      }
    ],
    "webTests": [
      {
        "url": "http://djtlsvpcjznwr2lx22cggeetjvzk75k6uzm5nhaoozbr3zqlfpb2fdid.onion/webtest",
        "statusCode": 200,
        "downloadSpeed": 2035,
        "uploadSpeed": 0,
        "dnsLookup": 0.019,
        "tcpConnection": 0.08399999999999999,
        "tlsHandshake": 0,
        "timeToFirstByte": 1193.4560000000001,
        "totalTime": 1193.5240000000001,
        "fcp": 0,
        "lcp": 0,
        "error": "Playwright error: page.goto: net::ERR_NAME_NOT_RESOLVED at http://djtlsvpcjznwr2lx22cggeetjvzk75k6uzm5nhaoozbr3zqlfpb2fdid.onion/webtest\nCall log:\n\u001b[2m  - navigating to \"http://djtlsvpcjznwr2lx22cggeetjvzk75k6uzm5nhaoozbr3zqlfpb2fdid.onion/webtest\", waiting until \"load\"\u001b[22m\n"
      }
    ],
    "totalDuration": 976210.0449420027,
    "setupDuration": 8529.162531999871,
    "diagnosticsDuration": 0.005168000236153603,
    "measurementDuration": 957676.618340997,
    "hasErrors": false,
    "errorCount": 0,
    "errors": []
  },
  {
    "toolName": "Ngtor",
    "measurementNumber": 11,
    "timestamp": 4546500.900606999,
    "fileTransfers": [
      {
        "filename": "10MB.txt",
        "timestamp": 4546500.907763002,
        "fileSize": 10485760,
        "contentType": "text/plain",
        "transferSuccess": true,
        "statusCode": 200,
        "downloadSpeed": 524009,
        "uploadSpeed": 0,
        "dnsLookup": 0.020999999999999998,
        "tcpConnection": 0.087,
        "tlsHandshake": 0,
        "timeToFirstByte": 927.6600000000001,
        "totalTransferTime": 20010.646,
        "hashMatch": true,
        "sizeMatch": true
      },
      {
        "filename": "1MB.txt",
        "timestamp": 4566552.468478,
        "fileSize": 1048576,
        "contentType": "text/plain",
        "transferSuccess": true,
        "statusCode": 200,
        "downloadSpeed": 374991,
        "uploadSpeed": 0,
        "dnsLookup": 0.019,
        "tcpConnection": 0.089,
        "tlsHandshake": 0,
        "timeToFirstByte": 1020.8170000000001,
        "totalTransferTime": 2796.2630000000004,
        "hashMatch": true,
        "sizeMatch": true
      },
      {
        "filename": "25MB.txt",
        "timestamp": 4569362.342016002,
        "fileSize": 26214400,
        "contentType": "text/plain",
        "transferSuccess": true,
        "statusCode": 200,
        "downloadSpeed": 624164,
        "uploadSpeed": 0,
        "dnsLookup": 0.038,
        "tcpConnection": 0.166,
        "tlsHandshake": 0,
        "timeToFirstByte": 1222.915,
        "totalTransferTime": 41999.21,
        "hashMatch": true,
        "sizeMatch": true
      }
    ],
    "webTests": [
      {
        "url": "http://djtlsvpcjznwr2lx22cggeetjvzk75k6uzm5nhaoozbr3zqlfpb2fdid.onion/webtest",
        "statusCode": 200,
        "downloadSpeed": 1960,
        "uploadSpeed": 0,
        "dnsLookup": 0.018000000000000002,
        "tcpConnection": 0.082,
        "tlsHandshake": 0,
        "timeToFirstByte": 1238.7440000000001,
        "totalTime": 1238.8110000000001,
        "fcp": 0,
        "lcp": 0,
        "error": "Playwright error: page.goto: net::ERR_NAME_NOT_RESOLVED at http://djtlsvpcjznwr2lx22cggeetjvzk75k6uzm5nhaoozbr3zqlfpb2fdid.onion/webtest\nCall log:\n\u001b[2m  - navigating to \"http://djtlsvpcjznwr2lx22cggeetjvzk75k6uzm5nhaoozbr3zqlfpb2fdid.onion/webtest\", waiting until \"load\"\u001b[22m\n"
      }
    ],
    "totalDuration": 976210.0449420027,
    "setupDuration": 8529.162531999871,
    "diagnosticsDuration": 0.005168000236153603,
    "measurementDuration": 957676.618340997,
    "hasErrors": false,
    "errorCount": 0,
    "errors": []
  },
  {
    "toolName": "Ngtor",
    "measurementNumber": 12,
    "timestamp": 4612867.073960001,
    "fileTransfers": [
      {
        "filename": "10MB.txt",
        "timestamp": 4612867.077166,
        "fileSize": 10485760,
        "contentType": "text/plain",
        "transferSuccess": true,
        "statusCode": 200,
        "downloadSpeed": 511496,
        "uploadSpeed": 0,
        "dnsLookup": 0.026,
        "tcpConnection": 0.11,
        "tlsHandshake": 0,
        "timeToFirstByte": 1153.3029999999999,
        "totalTransferTime": 20500.167999999998,
        "hashMatch": true,
        "sizeMatch": true
      },
      {
        "filename": "1MB.txt",
        "timestamp": 4633411.958651001,
        "fileSize": 1048576,
        "contentType": "text/plain",
        "transferSuccess": true,
        "statusCode": 200,
        "downloadSpeed": 425297,
        "uploadSpeed": 0,
        "dnsLookup": 0.019,
        "tcpConnection": 0.08399999999999999,
        "tlsHandshake": 0,
        "timeToFirstByte": 972.306,
        "totalTransferTime": 2465.509,
        "hashMatch": true,
        "sizeMatch": true
      },
      {
        "filename": "25MB.txt",
        "timestamp": 4635892.799229002,
        "fileSize": 26214400,
        "contentType": "text/plain",
        "transferSuccess": true,
        "statusCode": 200,
        "downloadSpeed": 661795,
        "uploadSpeed": 0,
        "dnsLookup": 0.020999999999999998,
        "tcpConnection": 0.092,
        "tlsHandshake": 0,
        "timeToFirstByte": 1372.318,
        "totalTransferTime": 39611.022,
        "hashMatch": true,
        "sizeMatch": true
      }
    ],
    "webTests": [
      {
        "url": "http://djtlsvpcjznwr2lx22cggeetjvzk75k6uzm5nhaoozbr3zqlfpb2fdid.onion/webtest",
        "statusCode": 200,
        "downloadSpeed": 1083,
        "uploadSpeed": 0,
        "dnsLookup": 0.02,
        "tcpConnection": 0.088,
        "tlsHandshake": 0,
        "timeToFirstByte": 2077.15,
        "totalTime": 2242.487,
        "fcp": 0,
        "lcp": 0,
        "error": "Playwright error: page.goto: net::ERR_NAME_NOT_RESOLVED at http://djtlsvpcjznwr2lx22cggeetjvzk75k6uzm5nhaoozbr3zqlfpb2fdid.onion/webtest\nCall log:\n\u001b[2m  - navigating to \"http://djtlsvpcjznwr2lx22cggeetjvzk75k6uzm5nhaoozbr3zqlfpb2fdid.onion/webtest\", waiting until \"load\"\u001b[22m\n"
      }
    ],
    "totalDuration": 976210.0449420027,
    "setupDuration": 8529.162531999871,
    "diagnosticsDuration": 0.005168000236153603,
    "measurementDuration": 957676.618340997,
    "hasErrors": false,
    "errorCount": 0,
    "errors": []
  },
  {
    "toolName": "Ngtor",
    "measurementNumber": 13,
    "timestamp": 4678028.414260002,
    "fileTransfers": [
      {
        "filename": "10MB.txt",
        "timestamp": 4678028.417060001,
        "fileSize": 10485760,
        "contentType": "text/plain",
        "transferSuccess": true,
        "statusCode": 200,
        "downloadSpeed": 663335,
        "uploadSpeed": 0,
        "dnsLookup": 0.038,
        "tcpConnection": 0.14100000000000001,
        "tlsHandshake": 0,
        "timeToFirstByte": 987.161,
        "totalTransferTime": 15807.634,
        "hashMatch": true,
        "sizeMatch": true
      },
      {
        "filename": "1MB.txt",
        "timestamp": 4693875.013075,
        "fileSize": 1048576,
        "contentType": "text/plain",
        "transferSuccess": true,
        "statusCode": 200,
        "downloadSpeed": 496895,
        "uploadSpeed": 0,
        "dnsLookup": 0.019,
        "tcpConnection": 0.08,
        "tlsHandshake": 0,
        "timeToFirstByte": 906.122,
        "totalTransferTime": 2110.255,
        "hashMatch": true,
        "sizeMatch": true
      },
      {
        "filename": "25MB.txt",
        "timestamp": 4696002.0261119995,
        "fileSize": 26214400,
        "contentType": "text/plain",
        "transferSuccess": true,
        "statusCode": 200,
        "downloadSpeed": 719593,
        "uploadSpeed": 0,
        "dnsLookup": 0.022,
        "tcpConnection": 0.106,
        "tlsHandshake": 0,
        "timeToFirstByte": 1167.45,
        "totalTransferTime": 36429.445999999996,
        "hashMatch": true,
        "sizeMatch": true
      }
    ],
    "webTests": [
      {
        "url": "http://djtlsvpcjznwr2lx22cggeetjvzk75k6uzm5nhaoozbr3zqlfpb2fdid.onion/webtest",
        "statusCode": 200,
        "downloadSpeed": 2286,
        "uploadSpeed": 0,
        "dnsLookup": 0.026,
        "tcpConnection": 0.091,
        "tlsHandshake": 0,
        "timeToFirstByte": 1062.073,
        "totalTime": 1062.168,
        "fcp": 0,
        "lcp": 0,
        "error": "Playwright error: page.goto: net::ERR_NAME_NOT_RESOLVED at http://djtlsvpcjznwr2lx22cggeetjvzk75k6uzm5nhaoozbr3zqlfpb2fdid.onion/webtest\nCall log:\n\u001b[2m  - navigating to \"http://djtlsvpcjznwr2lx22cggeetjvzk75k6uzm5nhaoozbr3zqlfpb2fdid.onion/webtest\", waiting until \"load\"\u001b[22m\n"
      }
    ],
    "totalDuration": 976210.0449420027,
    "setupDuration": 8529.162531999871,
    "diagnosticsDuration": 0.005168000236153603,
    "measurementDuration": 957676.618340997,
    "hasErrors": false,
    "errorCount": 0,
    "errors": []
  },
  {
    "toolName": "Ngtor",
    "measurementNumber": 14,
    "timestamp": 4733770.512390001,
    "fileTransfers": [
      {
        "filename": "10MB.txt",
        "timestamp": 4733770.514528999,
        "fileSize": 10485760,
        "contentType": "text/plain",
        "transferSuccess": true,
        "statusCode": 200,
        "downloadSpeed": 524613,
        "uploadSpeed": 0,
        "dnsLookup": 0.020999999999999998,
        "tcpConnection": 0.091,
        "tlsHandshake": 0,
        "timeToFirstByte": 1023.42,
        "totalTransferTime": 19987.573999999997,
        "hashMatch": true,
        "sizeMatch": true
      },
      {
        "filename": "1MB.txt",
        "timestamp": 4753794.209388999,
        "fileSize": 1048576,
        "contentType": "text/plain",
        "transferSuccess": true,
        "statusCode": 200,
        "downloadSpeed": 426524,
        "uploadSpeed": 0,
        "dnsLookup": 0.02,
        "tcpConnection": 0.096,
        "tlsHandshake": 0,
        "timeToFirstByte": 1030.92,
        "totalTransferTime": 2458.417,
        "hashMatch": true,
        "sizeMatch": true
      },
      {
        "filename": "25MB.txt",
        "timestamp": 4756270.004592,
        "fileSize": 26214400,
        "contentType": "text/plain",
        "transferSuccess": true,
        "statusCode": 200,
        "downloadSpeed": 702442,
        "uploadSpeed": 0,
        "dnsLookup": 0.04,
        "tcpConnection": 0.165,
        "tlsHandshake": 0,
        "timeToFirstByte": 1101.247,
        "totalTransferTime": 37318.933000000005,
        "hashMatch": true,
        "sizeMatch": true
      }
    ],
    "webTests": [
      {
        "url": "http://djtlsvpcjznwr2lx22cggeetjvzk75k6uzm5nhaoozbr3zqlfpb2fdid.onion/webtest",
        "statusCode": 200,
        "downloadSpeed": 2087,
        "uploadSpeed": 0,
        "dnsLookup": 0.019,
        "tcpConnection": 0.08600000000000001,
        "tlsHandshake": 0,
        "timeToFirstByte": 1163.766,
        "totalTime": 1163.815,
        "fcp": 0,
        "lcp": 0,
        "error": "Playwright error: page.goto: net::ERR_NAME_NOT_RESOLVED at http://djtlsvpcjznwr2lx22cggeetjvzk75k6uzm5nhaoozbr3zqlfpb2fdid.onion/webtest\nCall log:\n\u001b[2m  - navigating to \"http://djtlsvpcjznwr2lx22cggeetjvzk75k6uzm5nhaoozbr3zqlfpb2fdid.onion/webtest\", waiting until \"load\"\u001b[22m\n"
      }
    ],
    "totalDuration": 976210.0449420027,
    "setupDuration": 8529.162531999871,
    "diagnosticsDuration": 0.005168000236153603,
    "measurementDuration": 957676.618340997,
    "hasErrors": false,
    "errorCount": 0,
    "errors": []
  },
  {
    "toolName": "Ngtor",
    "measurementNumber": 15,
    "timestamp": 4795028.564864,
    "fileTransfers": [
      {
        "filename": "10MB.txt",
        "timestamp": 4795028.568818001,
        "fileSize": 10485760,
        "contentType": "text/plain",
        "transferSuccess": true,
        "statusCode": 200,
        "downloadSpeed": 511873,
        "uploadSpeed": 0,
        "dnsLookup": 0.018000000000000002,
        "tcpConnection": 0.08,
        "tlsHandshake": 0,
        "timeToFirstByte": 1141.316,
        "totalTransferTime": 20485.053,
        "hashMatch": true,
        "sizeMatch": true
      },
      {
        "filename": "1MB.txt",
        "timestamp": 4815551.743713001,
        "fileSize": 1048576,
        "contentType": "text/plain",
        "transferSuccess": true,
        "statusCode": 200,
        "downloadSpeed": 416621,
        "uploadSpeed": 0,
        "dnsLookup": 0.019,
        "tcpConnection": 0.083,
        "tlsHandshake": 0,
        "timeToFirstByte": 901.985,
        "totalTransferTime": 2516.858,
        "hashMatch": true,
        "sizeMatch": true
      },
      {
        "filename": "25MB.txt",
        "timestamp": 4818081.682017,
        "fileSize": 26214400,
        "contentType": "text/plain",
        "transferSuccess": true,
        "statusCode": 200,
        "downloadSpeed": 694457,
        "uploadSpeed": 0,
        "dnsLookup": 0.019,
        "tcpConnection": 0.083,
        "tlsHandshake": 0,
        "timeToFirstByte": 1100.556,
        "totalTransferTime": 37748.017,
        "hashMatch": true,
        "sizeMatch": true
      }
    ],
    "webTests": [
      {
        "url": "http://djtlsvpcjznwr2lx22cggeetjvzk75k6uzm5nhaoozbr3zqlfpb2fdid.onion/webtest",
        "statusCode": 200,
        "downloadSpeed": 2521,
        "uploadSpeed": 0,
        "dnsLookup": 0.027,
        "tcpConnection": 0.133,
        "tlsHandshake": 0,
        "timeToFirstByte": 963.207,
        "totalTime": 963.333,
        "fcp": 0,
        "lcp": 0,
        "error": "Playwright error: page.goto: net::ERR_NAME_NOT_RESOLVED at http://djtlsvpcjznwr2lx22cggeetjvzk75k6uzm5nhaoozbr3zqlfpb2fdid.onion/webtest\nCall log:\n\u001b[2m  - navigating to \"http://djtlsvpcjznwr2lx22cggeetjvzk75k6uzm5nhaoozbr3zqlfpb2fdid.onion/webtest\", waiting until \"load\"\u001b[22m\n"
      }
    ],
    "totalDuration": 976210.0449420027,
    "setupDuration": 8529.162531999871,
    "diagnosticsDuration": 0.005168000236153603,
    "measurementDuration": 957676.618340997,
    "hasErrors": false,
    "errorCount": 0,
    "errors": []
  }
]